Workbook

Sheet Assumptions
B2: Scenario Toggle | E2: =MATCH(C4,C11:C13,0) -> 2
C4: Base | D4: ¬Select cell to change Scenario
B5: Current Scenario
B7: Scenario Helper Table
C9: Scenario | D9: LFL rate | E9: NSO | F9: G&A Expense | G9: PPE Capex
D10: Percentages below are % of Revenue
B11: 1 | C11: Bear | D11: 0.03 | E11: 110 | F11: 0.085 | G11: 0.04
B12: 2 | C12: Base | D12: 0.04 | E12: 125 | F12: 0.07 | G12: 0.045
B13: 3 | C13: Bull | D13: 0.05 | E13: 140 | F13: 0.065 | G13: 0.05
B15: Assumptions
B16: Variable | H16: Fiscal Years Ending December 31, | P16: Source (Full Methodology in Appendix) | Q16: [1]
B17: All figures in $ 000s unless stated | H17: 2024 | I17: 2025 | J17: 2026 | K17: 2027 | L17: 2028 | M17: 2029 | N17: 2030
B19: Revenue Drivers
B20: NSO (Organic) (# of stores) | H20: 155 | I20: 113 | J20: =(INDEX(Assumptions!$B$11:$E$13,Assumptions!$E$2,4))-J22 -> 115 | K20: =INDEX(Assumptions!$B$11:$E$13,Assumptions!$E$2,4) -> 125 | L20: =INDEX(Assumptions!$B$11:$E$13,Assumptions!$E$2,4) -> 125 | M20: =INDEX(Assumptions!$B$11:$E$13,Assumptions!$E$2,4) -> 125 | N20: =INDEX(Assumptions!$B$11:$E$13,Assumptions!$E$2,4) -> 125 | P20: Scenario toggle; base 125, bear 110, bull 140
B21: LfL growth (% of revenue) | H21: -0.125 | I21: 0.097 | J21: =INDEX(Assumptions!$B$11:$E$13,Assumptions!$E$2,3) -> 0.04 | K21: =INDEX(Assumptions!$B$11:$E$13,Assumptions!$E$2,3) -> 0.04 | L21: =INDEX(Assumptions!$B$11:$E$13,Assumptions!$E$2,3) -> 0.04 | M21: =INDEX(Assumptions!$B$11:$E$13,Assumptions!$E$2,3) -> 0.04 | N21: =INDEX(Assumptions!$B$11:$E$13,Assumptions!$E$2,3) -> 0.04 | P21: Scenario toggle; base 5.0%, bear 4.0%, bull 6.0%
B22: Stores Acquired (# of stores) | H22: 0 | I22: 46 | J22: 10 | K22: 0 | L22: 0 | M22: 0 | N22: 0 | P22: Actuals only; zero from 2026
B23: Total number of Stores | H23: 2590 | I23: =H23+I20+I22 -> 2749 | J23: =I23+J20+J22 -> 2874 | K23: =J23+K20+K22 -> 2999 | L23: =K23+L20+L22 -> 3124 | M23: =L23+M20+M22 -> 3249 | N23: =M23+N20+N22 -> 3374
B24: Revenue per Store | H24: ='3- Statement Model'!$C$6/H23 -> 848.16641 | I24: ='3- Statement Model'!$D$6/I23 -> 912.63041 | J24: =(I24*(1+J21)) -> 949.13563 | K24: =(J24*(1+K21)) -> 987.10105 | L24: =(K24*(1+L21)) -> 1026.5851 | M24: =(L24*(1+M21)) -> 1067.6485 | N24: =(M24*(1+N21)) -> 1110.3544
B26: Operating Expenses
B27: COGS (% of revenue) | H27: =-'3- Statement Model'!$C$7/'3- Statement Model'!$C$6 -> 0.42452467 | I27: =-'3- Statement Model'!D7/'3- Statement Model'!D6 -> 0.41337704 | J27: 0.41 | K27: 0.41 | L27: 0.41 | M27: 0.41 | N27: 0.41 | P27: Slight improvement from 2025 actual (41.3%)
B28: S&A Expense (% of revenue) | H28: =-'3- Statement Model'!$C$10/'3- Statement Model'!$C$6 -> 0.28619903 | I28: =-'3- Statement Model'!$D$10/'3- Statement Model'!$D$6 -> 0.2849159 | J28: 0.285 | K28: 0.285 | L28: 0.285 | M28: 0.285 | N28: 0.285 | P28: 2-yr avg (2024: 28.62%; 2025: 28.49%)
B29: G&A Expense (% of revenue) | H29: =-'3- Statement Model'!$C$11/'3- Statement Model'!$C$6 -> 0.072547594 | I29: =-'3- Statement Model'!$D$11/'3- Statement Model'!$D$6 -> 0.069209402 | J29: =INDEX(Assumptions!$B$11:$F$13,Assumptions!$E$2,5) -> 0.07 | K29: =INDEX(Assumptions!$B$11:$F$13,Assumptions!$E$2,5) -> 0.07 | L29: =INDEX(Assumptions!$B$11:$F$13,Assumptions!$E$2,5) -> 0.07 | M29: =INDEX(Assumptions!$B$11:$F$13,Assumptions!$E$2,5) -> 0.07 | N29: =INDEX(Assumptions!$B$11:$F$13,Assumptions!$E$2,5) -> 0.07 | P29: Scenario toggle; base 7.0%, bear 7.5%, bull 6.5%
B30: EBITDA Margin (% of revenue) | H30: =1-(H27+H28+H29) -> 0.21672871 | I30: =1-(I27+I28+I29) -> 0.23249766 | J30: =1-(J27+J28+J29) -> 0.235 | K30: =1-(K27+K28+K29) -> 0.235 | L30: =1-(L27+L28+L29) -> 0.235 | M30: =1-(M27+M28+M29) -> 0.235 | N30: =1-(N27+N28+N29) -> 0.235 | P30: Plug; base 23.5%, bear 23.0%, bull 24.0%
B32: Financing and Tax
B33: Finance Income [LBO] | H33: 16116 | I33: 15508 | J33: 0 | K33: 0 | L33: 0 | M33: 0 | N33: 0 | P33: Zero - cash swept at LBO entry
B34: Finance Income (% of opening cash) [Hold Listed Scenario] | H34: 0.056 | I34: 0.0435 | J34: 0.04 | K34: 0.04 | L34: 0.04 | M34: 0.04 | N34: 0.04 | P34: 4.0% on opening cash - below 2-yr avg (4.98%) | Q34: [2]
B35: Lease Finance Costs (% of average lease balance) | H35: =-'3- Statement Model'!C$27/(('3- Statement Model'!C180+'3- Statement Model'!$C$185)/2) -> 0.059518625 | I35: =-('3- Statement Model'!D$27)/(('3- Statement Model'!D180+'3- Statement Model'!$D$185)/2) -> 0.067199048 | J35: 0.063 | K35: 0.063 | L35: 0.063 | M35: 0.063 | N35: 0.063 | P35: 6.3% - 3-yr avg adjusted upward for IBR increases
B36: Non-Lease Finance Costs | H36: 148 | I36: 42 | J36: 42 | K36: 42 | L36: 42 | M36: 42 | N36: 42 | P36: Frozen at 2025 actual ($42k) - bank charges only
P37: In the P&L, this also includes EOSB Interest
B38: Effective Income Tax Rate (% of PBT) | H38: =-'3- Statement Model'!C30/'3- Statement Model'!C28 -> 0.1204141 | I38: =-'3- Statement Model'!D30/'3- Statement Model'!D28 -> 0.14030248 | J38: 0.16 | K38: 0.16 | L38: 0.16 | M38: 0.16 | N38: 0.16 | P38: 16% - Pillar 2 full implementation
P39: Tax paid assumed equal to the full income tax charge
B41: Working Capital
B42: Inventory
B43: Inventory Days | H43: =-'3- Statement Model'!C51/'3- Statement Model'!C7*365 -> 52.602348 | I43: =-'3- Statement Model'!D51/'3- Statement Model'!D7*365 -> 54.579887 | J43: 54 | K43: 54 | L43: 54 | M43: 54 | N43: 54 | P43: Anchored to 2025 actual (54.6 days)
B45: Trade and Other Receivables
B46: AR Days | H46: ='3- Statement Model'!C212/'3- Statement Model'!C6*365 -> 5.7459539 | I46: ='3- Statement Model'!D212/'3- Statement Model'!D6*365 -> 7.5152592 | J46: 7.5 | K46: 7.5 | L46: 7.5 | M46: 7.5 | N46: 7.5 | P46: Anchored to 2025 actual (7.5 days)
B47: Prepaid Expenses (% of revenue) | H47: 0.0165 | I47: 0.0151 | J47: 0.015 | K47: 0.015 | L47: 0.015 | M47: 0.015 | N47: 0.015 | P47: 3-yr avg 1.61% (2023-2025); rounded to 1.5%
B48: Advances to Suppliers | H48: 2320 | I48: 1612 | J48: 1612 | K48: 1612 | L48: 1612 | M48: 1612 | N48: 1612 | P48: Frozen at 2025 actual ($1,612k) - immaterial
B49: Refundable Deposits | H49: 15373 | I49: 16100 | J49: 16100 | K49: 16100 | L49: 16100 | M49: 16100 | N49: 16100 | P49: Frozen at 2025 actual ($16,100k)
B50: Accrued income (% of revenue) | H50: ='3- Statement Model'!C216/'3- Statement Model'!C6 -> 0.006326616 | I50: ='3- Statement Model'!D216/'3- Statement Model'!D6 -> 0.0061367471 | J50: 0.006 | K50: 0.006 | L50: 0.006 | M50: 0.006 | N50: 0.006 | P50: 3-yr avg 0.59% (2023-2025); rounded to 0.6%
B51: Insurance receivables | H51: 433 | I51: 410 | J51: 410 | K51: 410 | L51: 410 | M51: 410 | N51: 410 | P51: Frozen at 2025 actual ($410k) - immaterial
B52: Staff Receivables | H52: 2330 | I52: 2553 | J52: 2553 | K52: 2553 | L52: 2553 | M52: 2553 | N52: 2553 | P52: Frozen at 2025 actual ($2,553k) - immaterial
B53: VAT receivable | H53: 5371 | I53: 4558 | J53: 4558 | K53: 4558 | L53: 4558 | M53: 4558 | N53: 4558 | P53: Frozen at 2025 actual ($4,558k) - immaterial
B54: Others | H54: 7200 | I54: 8494 | J54: 8494 | K54: 8494 | L54: 8494 | M54: 8494 | N54: 8494 | P54: Frozen at 2025 actual ($8,494k) - immaterial
B55: Non Current Portion | H55: 7498 | I55: 10784 | J55: 7500 | K55: 7500 | L55: 7500 | M55: 7500 | N55: 7500 | P55: Frozen at $7,500k - 2023/2024 avg
B57: Trade and Other Payables
B58: Total Trade payables (% of revenue) | H58: =('3- Statement Model'!C72+'3- Statement Model'!C65)/'3- Statement Model'!C6 -> 0.18745775 | I58: =('3- Statement Model'!D72+'3- Statement Model'!D65)/'3- Statement Model'!D6 -> 0.18547676 | J58: 0.1865 | K58: 0.1865 | L58: 0.1865 | M58: 0.1865 | N58: 0.1865 | P58: 2-yr avg 18.65% (2024: 18.75%; 2025: 18.55%)
B59: Non-Current Trade and other Payables | H59: 19760 | I59: 2729 | J59: 2729 | K59: 2729 | L59: 2729 | M59: 2729 | N59: 2729 | P59: Frozen at 2025 actual ($2,729k) - immaterial
B61: Fixed Assets
B62: Property and Equipment
B63: PPE Capex (% of revenue) | H63: ='3- Statement Model'!C159/'3- Statement Model'!C6 -> 0.048528941 | I63: ='3- Statement Model'!D159/'3- Statement Model'!D6 -> 0.03781896 | J63: =INDEX(Assumptions!$B$11:$G$13,Assumptions!$E$2,6) -> 0.045 | K63: =INDEX(Assumptions!$B$11:$G$13,Assumptions!$E$2,6) -> 0.045 | L63: =INDEX(Assumptions!$B$11:$G$13,Assumptions!$E$2,6) -> 0.045 | M63: =INDEX(Assumptions!$B$11:$G$13,Assumptions!$E$2,6) -> 0.045 | N63: =INDEX(Assumptions!$B$11:$G$13,Assumptions!$E$2,6) -> 0.045 | P63: Scenario toggle; base 4.5%, bear 4.0%, bull 5.0%
B64: Disposals | H64: =-43694+41334 -> -2360 | I64: =-32046+29355 -> -2691 | J64: -2691 | K64: -2691 | L64: -2691 | M64: -2691 | N64: -2691 | P64: Frozen at 2025 actual ($2,691k) - immaterial
B65: Depreciation (% of Opening PPE) | H65: ='3- Statement Model'!C160/'3- Statement Model'!C158 -> -0.248964 | I65: ='3- Statement Model'!D160/'3- Statement Model'!D158 -> -0.26398508 | J65: 0.26 | K65: 0.26 | L65: 0.26 | M65: 0.26 | N65: 0.26 | P65: 4-yr avg 25.9% (2022-2025); rounded to 26.0%
B66: Other Adjustments | H66: -21239 | I66: 7242 | J66: 0 | K66: 0 | L66: 0 | M66: 0 | N66: 0 | P66: Zero - hyperinflation/FX, non-operating
B68: Right of Use Assets
B69: Addition to RoU per NSO | H69: ='3- Statement Model'!C170/Assumptions!H20 -> 1802.5806 | I69: ='3- Statement Model'!D170/(Assumptions!I20) -> 2258.0708 | J69: 2000 | K69: 2000 | L69: 2000 | M69: 2000 | N69: 2000 | P69: 2-yr avg $2,031k/store; rounded to $2,000k
B70: Depreciation (% of Opening Balance) | H70: =-'3- Statement Model'!C171/'3- Statement Model'!C169 -> 0.36872396 | I70: =-'3- Statement Model'!D171/'3- Statement Model'!D169 -> 0.36315617 | J70: 0.36 | K70: 0.36 | L70: 0.36 | M70: 0.36 | N70: 0.36 | P70: 2-yr avg 36.59% (2024-2025); rounded to 36.0%
B71: Terminations | H71: -16217 | I71: -7179 | J71: -7179 | K71: -7179 | L71: -7179 | M71: -7179 | N71: -7179 | P71: Frozen at 2025 actual ($7,179k)
B72: Lease Liability
B73: Additions & Terminations | P73: Equal to RoU asset movements - see RoU assumptions
B74: Principal Payment (% Of Opening Balance) | H74: =-'3- Statement Model'!C182/'3- Statement Model'!C180 -> 0.35410957 | I74: =-'3- Statement Model'!D182/'3- Statement Model'!D180 -> 0.33240272 | J74: 0.35 | K74: 0.35 | L74: 0.35 | M74: 0.35 | N74: 0.35 | P74: 3-yr avg 36.2% (2023-2025); rounded to 35.0%
B75: Current/Total Lease Liability | H75: ='3- Statement Model'!C187/'3- Statement Model'!C185 -> 0.32753947 | I75: ='3- Statement Model'!D187/'3- Statement Model'!D185 -> 0.32655702 | J75: 0.33 | K75: 0.33 | L75: 0.33 | M75: 0.33 | N75: 0.33 | P75: Frozen at 33.0% - 3-yr avg (2023-2025: 32.7%)
B77: Investment Property | H77: 3356 | I77: 3712 | J77: 3712 | K77: 3712 | L77: 3712 | M77: 3712 | N77: 3712 | P77: Frozen at 2025 actual ($3,712k) - immaterial
B79: Intangibles
B80: Core Intangibles
B81: Intangibles Capex (% of revenue) | H81: ='3- Statement Model'!C195/'3- Statement Model'!C6 -> 0.0078292897 | I81: ='3- Statement Model'!D195/'3- Statement Model'!D6 -> 0.0048688209 | J81: 0.006 | K81: 0.006 | L81: 0.006 | M81: 0.006 | N81: 0.006 | P81: 4-yr avg 0.59%; rounded to 0.6%
B82: Disposals | H82: =-4292+1739 -> -2553 | I82: =-4343+2351 -> -1992 | J82: -1992 | K82: -1992 | L82: -1992 | M82: -1992 | N82: -1992 | P82: Frozen at 2025 actual ($1,992k) - immaterial
B83: Amortization (% of Opening balance) | H83: =-'3- Statement Model'!C196/'3- Statement Model'!C194 -> 0.18809326 | I83: =-'3- Statement Model'!D196/'3- Statement Model'!D194 -> 0.24568842 | J83: 0.2 | K83: 0.2 | L83: 0.2 | M83: 0.2 | N83: 0.2 | P83: 4-yr avg 20.2% (volatile series); rounded to 20.0%
B84: MAT Franchise Rights
B85: Additions | H85: 0 | I85: 0 | J85: 20830 | K85: 0 | L85: 0 | M85: 0 | N85: 0 | P85: 2026 only: $20,830k acquisition cost
B86: Amortization (% of Opening balance) | H86: 0 | I86: 0 | J86: =100%/75*10/12 -> 0.011111111 | K86: =100%/75 -> 0.013333333 | L86: =100%/75 -> 0.013333333 | M86: =100%/75 -> 0.013333333 | N86: =100%/75 -> 0.013333333 | P86: 1.33% p.a. over 75-yr exclusive franchise term
B88: Other Balance Sheet Items
B89: Deferred Tax Asset | H89: 2280 | I89: 3594 | J89: 3594 | K89: 3594 | L89: 3594 | M89: 3594 | N89: 3594 | P89: Frozen at 2025 actual ($3,594k) - immaterial
B90: Deferred Tax Liabilities | H90: 2015 | I90: 2110 | J90: 2110 | K90: 2110 | L90: 2110 | M90: 2110 | N90: 2110 | P90: Frozen at 2025 actual ($2,110k) - immaterial
B91: Income tax, zakat, other deductions payable | H91: 17854 | I91: 36745 | J91: 36745 | K91: 36745 | L91: 36745 | M91: 36745 | N91: 36745 | P91: Frozen at 2025 actual ($36,745k) - timing driven
B92: Due to related parties | H92: 13262 | I92: 16681 | J92: =I92 -> 16681 | K92: =J92 -> 16681 | L92: =K92 -> 16681 | M92: =L92 -> 16681 | N92: =M92 -> 16681 | P92: Frozen at 2025 actual ($16,681k)
B93: Provisions for legal, tax and other claims | H93: 17141 | I93: 15077 | J93: =I93 -> 15077 | K93: =J93 -> 15077 | L93: =K93 -> 15077 | M93: =L93 -> 15077 | N93: =M93 -> 15077 | P93: Frozen at 2025 actual ($15,077k) - event-driven
B95: Other Reserves | H95: -28895 | I95: -22819 | J95: -25795 | K95: -25795 | L95: -25795 | M95: -25795 | N95: -25795 | P95: Frozen at post-LBO Day 1 balance
B96: NCI | H96: 3686 | I96: 984 | J96: 984 | K96: 984 | L96: 984 | M96: 984 | N96: 984 | P96: Frozen at 2025 actual ($984k) - residual
B98: Provision for End of Service Benefits
B99: EOSB Interest (% of Opening balance) | H99: =3326/68561 -> 0.048511544 | I99: =3226/'3- Statement Model'!C64 -> 0.047180987 | J99: 0.0469 | K99: 0.0469 | L99: 0.0469 | M99: 0.0469 | N99: 0.0469 | P99: 3-yr avg 4.69% (2023-2025); 2022 excluded (outlier)
B100: EOSB Service Charge (% of Opening balance) | H100: 0.149 | I100: 0.145 | J100: 0.147 | K100: 0.147 | L100: 0.147 | M100: 0.147 | N100: 0.147 | P100: 3-yr avg 14.7% (2023-2025); 2022 excluded (outlier)
B101: EOSB Payments (% of Opening balance) | H101: 0.206 | I101: 0.162 | J101: 0.162 | K101: 0.162 | L101: 0.162 | M101: 0.162 | N101: 0.162 | P101: 2025 actual 16.2%; 2024 excluded (elevated)
B103: Cash Flow Statement Items
B104: Dividends Paid to shareholders (LBO) | H104: 179424 | I104: 126987 | J104: 201567 | K104: 0 | L104: 0 | M104: 0 | N104: 0 | P104: Zero post-LBO; 2026 pre-close dividend $201,567k
B105: Dividend Payout ratio (% of Net Profits) (Hold-Listed Scenario) | J105: =J104/'3- Statement Model'!D31 -> 0.92271458 | K105: 0.9 | L105: 0.9 | M105: 0.9 | N105: 0.9 | P105: 90% of prior year NP - 2-yr avg (2024: 84%; 2025: 92%)
B106: Key Money Paid | H106: -504 | I106: -1680 | J106: -1100 | K106: -1100 | L106: -1100 | M106: -1100 | N106: -1100 | P106: 2-yr avg $1,092k (2024: $504k; 2025: $1,680k)
B107: Proceeds from Disposal of PPE | H107: 2441 | I107: 1222 | J107: 1700 | K107: 1700 | L107: 1700 | M107: 1700 | N107: 1700 | P107: 3-yr avg $1,720k; rounded to $1,700k
B108: Acquisition of Subsidiary | H108: 0 | I108: -10565 | J108: -20830 | K108: 0 | L108: 0 | M108: 0 | N108: 0 | P108: 2026 only: $20,830k - MAT acquisition

Sheet 3- Statement Model
B2: Income Statement
E3: Fiscal Years Ending December 31,
B4: ($ in 000s) | C4: 2024 | D4: 2025 | E4: 2026 | F4: 2027 | G4: 2028 | H4: 2029 | I4: 2030
B6: Revenue | C6: 2196751 | D6: 2508821 | E6: =Assumptions!J23*Assumptions!J24 -> 2727815.8 | F6: =Assumptions!K23*Assumptions!K24 -> 2960316.1 | G6: =Assumptions!L23*Assumptions!L24 -> 3207051.8 | H6: =Assumptions!M23*Assumptions!M24 -> 3468790 | I6: =Assumptions!N23*Assumptions!N24 -> 3746335.9 | K6: =I6/D6 -> 1.4932655 | L6: =K6^(1/5) -> 1.0834962
B7: COGS | C7: =-1029357+96782 -> -932575 | D7: =-1143928+106839 -> -1037089 | E7: =-E6*Assumptions!J27 -> -1118404.5 | F7: =-F6*Assumptions!K27 -> -1213729.6 | G7: =-G6*Assumptions!L27 -> -1314891.3 | H7: =-H6*Assumptions!M27 -> -1422203.9 | I7: =-I6*Assumptions!N27 -> -1535997.7
B8: Gross Profit | C8: =C6+C7 -> 1264176 | D8: =D6+D7 -> 1471732 | E8: =E6+E7 -> 1609411.3 | F8: =F6+F7 -> 1746586.5 | G8: =G6+G7 -> 1892160.6 | H8: =H6+H7 -> 2046586.1 | I8: =I6+I7 -> 2210338.2
B10: S&A Expense | C10: =-784704+155996 -> -628708 | D10: =-886102+171299 -> -714803 | E10: =-E6*Assumptions!J28 -> -777427.5 | F10: =-F6*Assumptions!K28 -> -843690.08 | G10: =-G6*Assumptions!L28 -> -914009.77 | H10: =-H6*Assumptions!M28 -> -988605.14 | I10: =-I6*Assumptions!N28 -> -1067705.7
B11: G&A Expense | C11: =-184744+25375 -> -159369 | D11: =-202562+28928 -> -173634 | E11: =-E6*Assumptions!J29 -> -190947.11 | F11: =-F6*Assumptions!K29 -> -207222.12 | G11: =-G6*Assumptions!L29 -> -224493.63 | H11: =-H6*Assumptions!M29 -> -242815.3 | I11: =-I6*Assumptions!N29 -> -262243.51
B12: Other Income | C12: 7461 | D12: 13361 | E12: =-E105 -> -2983 | F12: =-F105 -> -2983 | G12: =-G105 -> -2983 | H12: =-H105 -> -2983 | I12: =-I105 -> -2983 | J12: [3]
B13: Loss/Gain due to Hyperinflation | C13: 125 | D13: -1052 | E13: 0 | F13: 0 | G13: 0 | H13: 0 | I13: 0
B14: EBITDA | C14: =C8+C10+C11+C12+C13 -> 483685 | D14: =D8+D10+D11+D12+D13 -> 595604 | E14: =E8+E10+E11+E12+E13 -> 638053.71 | F14: =F8+F10+F11+F12+F13 -> 692691.27 | G14: =G8+G10+G11+G12+G13 -> 750674.18 | H14: =H8+H10+H11+H12+H13 -> 812182.64 | I14: =I8+I10+I11+I12+I13 -> 877405.93
B16: D&A | C16: -278153 | D16: -307066 | E16: =E17+E18 -> -321555.06 | F16: =F17+F18 -> -331130.6 | G16: =G17+G18 -> -348295.37 | H16: =H17+H18 -> -363425.07 | I16: =I17+I18 -> -377536.96
B17: Non-RoU Assets | C17: =C160+C196-195 -> -94343 | D17: =D160+D196-167 -> -101500 | E17: =E160+E196+E203 -> -101659.14 | F17: =F160+F196+F203 -> -110181.65 | G17: =G160+G196+G203 -> -119472.48 | H17: =H160+H196+H203 -> -129562.86 | I17: =I160+I196+I203 -> -140449.58
B18: RoU Assets | C18: =C$171 -> -183810 | D18: =D$171 -> -205566 | E18: =E$171 -> -219895.92 | F18: =F$171 -> -220948.95 | G18: =G$171 -> -228822.89 | H18: =H$171 -> -233862.21 | I18: =I$171 -> -237087.37
B19: EBIT | C19: =C14+C16 -> 205532 | D19: =D14+D16 -> 288538 | E19: =E14+E16 -> 316498.65 | F19: =F14+F16 -> 361560.67 | G19: =G14+G16 -> 402378.81 | H19: =H14+H16 -> 448757.57 | I19: =I14+I16 -> 499868.97
B21: Impairment losses | C21: =-12631-1093 -> -13724 | D21: =-5559-251 -> -5810 | E21: 0 | F21: 0 | G21: 0 | H21: 0 | I21: 0
B22: Operating Profit | C22: =SUM(C19:C21) -> 191808 | D22: =SUM(D19:D21) -> 282728 | E22: =SUM(E19:E21) -> 316498.65 | F22: =SUM(F19:F21) -> 361560.67 | G22: =SUM(G19:G21) -> 402378.81 | H22: =SUM(H19:H21) -> 448757.57 | I22: =SUM(I19:I21) -> 499868.97
B24: Finance Income | C24: 16116 | D24: 15508 | E24: =Assumptions!J33 -> 0 | F24: =Assumptions!K33 -> 0 | G24: =Assumptions!L33 -> 0 | H24: =Assumptions!M33 -> 0 | I24: =Assumptions!N33 -> 0
B25: Finance Costs | C25: -35793 | D25: -44135 | E25: =E26+E27 -> -43476.447 | F25: =F26+F27 -> -44139.935 | G25: =G26+G27 -> -45241.624 | H25: =H26+H27 -> -45999.432 | I25: =I26+I27 -> -46535.048
B26: Non Lease Finance Costs | C26: =-3326-148 -> -3474 | D26: =-3226-42 -> -3268 | E26: =-(Assumptions!J36+'3- Statement Model'!E231) -> -3359.9405 | F26: =-(Assumptions!K36+'3- Statement Model'!F231) -> -3465.7828 | G26: =-(Assumptions!L36+'3- Statement Model'!G231) -> -3575.0015 | H26: =-(Assumptions!M36+'3- Statement Model'!H231) -> -3687.7042 | I26: =-(Assumptions!N36+'3- Statement Model'!I231) -> -3804.0022
B27: Lease Finance Costs | C27: -32319 | D27: -40867 | E27: =-((E180+E185)/2)*Assumptions!J35 -> -40116.507 | F27: =-((F180+F185)/2)*Assumptions!K35 -> -40674.152 | G27: =-((G180+G185)/2)*Assumptions!L35 -> -41666.622 | H27: =-((H180+H185)/2)*Assumptions!M35 -> -42311.727 | I27: =-((I180+I185)/2)*Assumptions!N35 -> -42731.046
B28: Profit before Tax | C28: =C22+C24+C25 -> 172131 | D28: =D22+D24+D25 -> 254101 | E28: =E22+E24+E25 -> 273022.2 | F28: =F22+F24+F25 -> 317420.74 | G28: =G22+G24+G25 -> 357137.19 | H28: =H22+H24+H25 -> 402758.14 | I28: =I22+I24+I25 -> 453333.93
B30: Income taxes and Zakat | C30: -20727 | D30: -35651 | E30: =-E28*Assumptions!J38 -> -43683.552 | F30: =-F28*Assumptions!K38 -> -50787.318 | G30: =-G28*Assumptions!L38 -> -57141.95 | H30: =-H28*Assumptions!M38 -> -64441.303 | I30: =-I28*Assumptions!N38 -> -72533.428
B31: Net Profit | C31: =C28+C30 -> 151404 | D31: =D28+D30 -> 218450 | E31: =E28+E30 -> 229338.65 | F31: =F28+F30 -> 266633.42 | G31: =G28+G30 -> 299995.24 | H31: =H28+H30 -> 338316.84 | I31: =I28+I30 -> 380800.5
C32: =C31/C6 -> 0.068921785 | D32: =D31/D6 -> 0.087072772 | E32: =E31/E6 -> 0.084074096 | F32: =F31/F6 -> 0.09006924 | G32: =G31/G6 -> 0.093542373 | H32: =H31/H6 -> 0.097531659 | I32: =I31/I6 -> 0.10164612
B34: Balance Sheet
E35: Fiscal Years Ending December 31,
B36: ($ in 000s) | C36: =C$4 -> 2024 | D36: =D$4 -> 2025 | E36: =E$4 -> 2026 | F36: =F$4 -> 2027 | G36: =G$4 -> 2028 | H36: =H$4 -> 2029 | I36: =I$4 -> 2030
B38: ASSETS
B40: Non-Current Assets
B41: Property and Equipment | C41: 328761 | D41: 341405 | E41: =E163 -> 372700.41 | F41: =F163 -> 406321.53 | G41: =G163 -> 442304.26 | H41: =H163 -> 480709.7 | I41: =I163 -> 521619.29
B42: Right of Use Assets | C42: 566054 | D42: 610822 | E42: =E174 -> 613747.08 | F42: =F174 -> 635619.13 | G42: =G174 -> 649617.24 | H42: =H174 -> 658576.04 | I42: =I174 -> 664309.66
B43: Investment Property | C43: 3356 | D43: 3712 | E43: =Assumptions!J77 -> 3712 | F43: =Assumptions!K77 -> 3712 | G43: =Assumptions!L77 -> 3712 | H43: =Assumptions!M77 -> 3712 | I43: =Assumptions!N77 -> 3712
B44: Intangibles | C44: 59201 | D44: 63312 | E44: =E206 -> 85623.05 | F44: =F206 -> 88113.4 | G44: =G206 -> 91534.827 | H44: =H206 -> 95791.814 | I44: =I206 -> 100812.77
B45: Trade and other Receivables | C45: 7498 | D45: 10784 | E45: =E223 -> 7500 | F45: =F223 -> 7500 | G45: =G223 -> 7500 | H45: =H223 -> 7500 | I45: =I223 -> 7500
B46: Long term Deposits with Banks | C46: 0 | D46: 117838 | E46: 0 | F46: 0 | G46: 0 | H46: 0 | I46: 0 | J46: [4]
B47: Deferred Tax Asset | C47: 2280 | D47: 3594 | E47: =Assumptions!J89 -> 3594 | F47: =Assumptions!K89 -> 3594 | G47: =Assumptions!L89 -> 3594 | H47: =Assumptions!M89 -> 3594 | I47: =Assumptions!N89 -> 3594
B48: Non-Current Assets | C48: =SUM(C41:C47) -> 967150 | D48: =SUM(D41:D47) -> 1151467 | E48: =SUM(E41:E47) -> 1086876.5 | F48: =SUM(F41:F47) -> 1144860.1 | G48: =SUM(G41:G47) -> 1198262.3 | H48: =SUM(H41:H47) -> 1249883.6 | I48: =SUM(I41:I47) -> 1301547.7
B50: Current Assets
B51: Inventories | C51: 134399 | D51: 155080 | E51: =-E7*Assumptions!J43/365 -> 165462.58 | F51: =-F7*Assumptions!K43/365 -> 179565.47 | G51: =-G7*Assumptions!L43/365 -> 194531.86 | H51: =-H7*Assumptions!M43/365 -> 210408.25 | I51: =-I7*Assumptions!N43/365 -> 227243.5
B52: Trade and Other Receivables | C52: 110421 | D52: 128007 | E52: =E224 -> 139562.14 | F52: =F224 -> 149222.05 | G52: =G224 -> 159473.41 | H52: =H224 -> 170348.1 | I52: =I224 -> 181879.56
B53: Due from Related Parties | C53: 265 | D53: 0 | E53: 0 | F53: 0 | G53: 0 | H53: 0 | I53: 0
B54: Short Term Deposits with Banks | C54: 213695 | D54: 145235 | E54: 0 | F54: 0 | G54: 0 | H54: 0 | I54: 0 | J54: [5]
B55: Cash and Cash Equivalents | C55: 81470 | D55: 154337 | E55: =E153 -> 278427.7 | F55: =F153 -> 528099.99 | G55: =G153 -> 810306.31 | H55: =H153 -> 1129612.4 | I55: =I153 -> 1489947.1
B56: Current Assets | C56: =SUM(C51:C52,C53:C55) -> 540250 | D56: =SUM(D51:D52,D53:D55) -> 582659 | E56: =SUM(E51:E52,E53:E55) -> 583452.42 | F56: =SUM(F51:F52,F53:F55) -> 856887.51 | G56: =SUM(G51:G52,G53:G55) -> 1164311.6 | H56: =SUM(H51:H52,H53:H55) -> 1510368.8 | I56: =SUM(I51:I52,I53:I55) -> 1899070.2
B58: Total Assets | C58: =C48+C56 -> 1507400 | D58: =D48+D56 -> 1734126 | E58: =E48+E56 -> 1670329 | F58: =F48+F56 -> 2001747.6 | G58: =G48+G56 -> 2362573.9 | H58: =H48+H56 -> 2760252.3 | I58: =I48+I56 -> 3200617.9
B60: LIABILITIES AND EQUITY
B62: Non-Current Liabilities
B63: Lease Liabilities | C63: 389241 | D63: 429297 | E63: =E188 -> 426169.51 | F63: =F188 -> 438963.25 | G63: =G188 -> 447279.18 | H63: =H188 -> 452684.54 | I63: =I188 -> 456198.02
B64: Provision for Employee's EOSB | C64: 68375 | D64: 70745 | E64: =E235 -> 73001.765 | F64: =F235 -> 75330.522 | G64: =G235 -> 77733.565 | H64: =H235 -> 80213.266 | I64: =I235 -> 82772.069
B65: Trade and other Payables | C65: 19760 | D65: 2729 | E65: =Assumptions!J59 -> 2729 | F65: =Assumptions!K59 -> 2729 | G65: =Assumptions!L59 -> 2729 | H65: =Assumptions!M59 -> 2729 | I65: =Assumptions!N59 -> 2729
B66: Deferred tax Liabilities | C66: 2015 | D66: 2110 | E66: =Assumptions!J90 -> 2110 | F66: =Assumptions!K90 -> 2110 | G66: =Assumptions!L90 -> 2110 | H66: =Assumptions!M90 -> 2110 | I66: =Assumptions!N90 -> 2110
B67: Total Non-Current Liabilities | C67: =SUM(C63:C66) -> 479391 | D67: =SUM(D63:D66) -> 504881 | E67: =SUM(E63:E66) -> 504010.28 | F67: =SUM(F63:F66) -> 519132.78 | G67: =SUM(G63:G66) -> 529851.75 | H67: =SUM(H63:H66) -> 537736.81 | I67: =SUM(I63:I66) -> 543809.09
B69: Current Liabilities
B70: Lease Liabilities | C70: 189590 | D70: 208169 | E70: =E187 -> 209904.39 | F70: =F187 -> 216205.78 | G70: =G187 -> 220301.69 | H70: =H187 -> 222964.03 | I70: =I187 -> 224694.55
B71: Income tax, zakat, other deductions payable | C71: 17854 | D71: 36745 | E71: =Assumptions!J91 -> 36745 | F71: =Assumptions!K91 -> 36745 | G71: =Assumptions!L91 -> 36745 | H71: =Assumptions!M91 -> 36745 | I71: =Assumptions!N91 -> 36745
B72: Trade and other Payables | C72: 392038 | D72: 462599 | E72: =(E6*Assumptions!J58)-Assumptions!J59 -> 506008.65 | F72: =(F6*Assumptions!K58)-Assumptions!K59 -> 549369.94 | G72: =(G6*Assumptions!L58)-Assumptions!L59 -> 595386.17 | H72: =(H6*Assumptions!M58)-Assumptions!M59 -> 644200.33 | I72: =(I6*Assumptions!N58)-Assumptions!N59 -> 695962.64
B73: Due to related parties | C73: 13262 | D73: 16681 | E73: =Assumptions!J92 -> 16681 | F73: =Assumptions!K92 -> 16681 | G73: =Assumptions!L92 -> 16681 | H73: =Assumptions!M92 -> 16681 | I73: =Assumptions!N92 -> 16681
B74: Provisions for legal, tax and other claims | C74: 17141 | D74: 15077 | E74: =Assumptions!J93 -> 15077 | F74: =Assumptions!K93 -> 15077 | G74: =Assumptions!L93 -> 15077 | H74: =Assumptions!M93 -> 15077 | I74: =Assumptions!N93 -> 15077
B75: Total Current Liabilities | C75: =SUM(C70:C74) -> 629885 | D75: =SUM(D70:D74) -> 739271 | E75: =SUM(E70:E74) -> 784416.03 | F75: =SUM(F70:F74) -> 834078.73 | G75: =SUM(G70:G74) -> 884190.86 | H75: =SUM(H70:H74) -> 935667.36 | I75: =SUM(I70:I74) -> 989160.19
B77: Total Liabilities | C77: =C67+C75 -> 1109276 | D77: =D67+D75 -> 1244152 | E77: =E67+E75 -> 1288426.3 | F77: =F67+F75 -> 1353211.5 | G77: =G67+G75 -> 1414042.6 | H77: =H67+H75 -> 1473404.2 | I77: =I67+I75 -> 1532969.3
B79: Equity
B80: Share Capital | C80: 168473 | D80: 168473 | E80: 168473 | F80: 168473 | G80: 168473 | H80: 168473 | I80: 168473
B81: Treasury Shares | C81: -16749 | D81: -16749 | E81: -16749 | F81: -16749 | G81: -16749 | H81: -16749 | I81: -16749
B82: Retained Earnings | C82: 271609 | D82: 360085 | E82: =D82+E31-D46-D54-'LBO Model'!C39+2976+E140 -> 254989.65 | F82: =E82+F31 -> 521623.07 | G82: =F82+G31 -> 821618.31 | H82: =G82+H31 -> 1159935.1 | I82: =H82+I31 -> 1540735.6
B83: Other Reserves | C83: -28895 | D83: -22819 | E83: =Assumptions!J95 -> -25795 | F83: =Assumptions!K95 -> -25795 | G83: =Assumptions!L95 -> -25795 | H83: =Assumptions!M95 -> -25795 | I83: =Assumptions!N95 -> -25795
B84: NCI | C84: 3686 | D84: 984 | E84: 984 | F84: 984 | G84: 984 | H84: 984 | I84: 984
B85: Total Equity | C85: =SUM(C80:C84) -> 398124 | D85: =SUM(D80:D84) -> 489974 | E85: =SUM(E80:E84) -> 381902.65 | F85: =SUM(F80:F84) -> 648536.07 | G85: =SUM(G80:G84) -> 948531.31 | H85: =SUM(H80:H84) -> 1286848.1 | I85: =SUM(I80:I84) -> 1667648.6
B87: Total Liabilities and Equity | C87: =C85+C77 -> 1507400 | D87: =D85+D77 -> 1734126 | E87: =E85+E77 -> 1670329 | F87: =F85+F77 -> 2001747.6 | G87: =G85+G77 -> 2362573.9 | H87: =H85+H77 -> 2760252.3 | I87: =I85+I77 -> 3200617.9
B89: Balance sheet check | C89: =C58-C87 -> 0 | D89: =D58-D87 -> 0 | E89: =E58-E87 -> 0 | F89: =F58-F87 -> 0 | G89: =G58-G87 -> 0 | H89: =H58-H87 -> 0 | I89: =I58-I87 -> 0
B92: Cash Flow Statement
E93: Fiscal Years Ending December 31,
B94: ($ in 000s) | C94: =C$4 -> 2024 | D94: =D$4 -> 2025 | E94: =E$4 -> 2026 | F94: =F$4 -> 2027 | G94: =G$4 -> 2028 | H94: =H$4 -> 2029 | I94: =I$4 -> 2030
B96: Cash Flow from Operating Activities
B98: Profit before income tax and zakat for the year | C98: =C$28 -> 172131 | D98: =D$28 -> 254101 | E98: =E$28 -> 273022.2 | F98: =F$28 -> 317420.74 | G98: =G$28 -> 357137.19 | H98: =H$28 -> 402758.14 | I98: =I$28 -> 453333.93
B99: Adjustments:
B100: Depreciation and Amortisation | C100: =-C16 -> 278153 | D100: =-D16 -> 307066 | E100: =-E16 -> 321555.06 | F100: =-F16 -> 331130.6 | G100: =-G16 -> 348295.37 | H100: =-H16 -> 363425.07 | I100: =-I16 -> 377536.96
B101: EOSB | C101: 10220 | D101: 9878 | E101: =E230 -> 10399.515 | F101: =F230 -> 10731.26 | G101: =G230 -> 11073.587 | H101: =H230 -> 11426.834 | I101: =I230 -> 11791.35
B102: Impairment Allowance for financial assets | C102: 1093 | D102: 251 | E102: 0 | F102: 0 | G102: 0 | H102: 0 | I102: 0
B103: Provision for obsolete inventory | C103: 1978 | D103: 2662 | E103: 0 | F103: 0 | G103: 0 | H103: 0 | I103: 0
B104: Impairment of non-financial assets | C104: 12631 | D104: 5559 | E104: 0 | F104: 0 | G104: 0 | H104: 0 | I104: 0
B105: Loss on disposal of PPE and intangible assets | C105: 1862 | D105: 2591 | E105: =-(E161+E197)-E129 -> 2983 | F105: =-(F161+F197)-F129 -> 2983 | G105: =-(G161+G197)-G129 -> 2983 | H105: =-(H161+H197)-H129 -> 2983 | I105: =-(I161+I197)-I129 -> 2983
B106: Employee Benefit expense - share based payments | C106: 1382 | D106: 1594 | E106: 0 | F106: 0 | G106: 0 | H106: 0 | I106: 0
B107: Finance Income | C107: -16116 | D107: -15508 | E107: =E24 -> 0 | F107: =F24 -> 0 | G107: =G24 -> 0 | H107: =H24 -> 0 | I107: =I24 -> 0
B108: Finance Costs | C108: 35793 | D108: 44135 | E108: =-E25 -> 43476.447 | F108: =-F25 -> 44139.935 | G108: =-G25 -> 45241.624 | H108: =-H25 -> 45999.432 | I108: =-I25 -> 46535.048
B109: Hyperinflation Impact | C109: 600 | D109: 1088 | E109: 0 | F109: 0 | G109: 0 | H109: 0 | I109: 0
B111: Operating Cash Flows before WC changes | C111: =SUM(C98:C109) -> 499727 | D111: =SUM(D98:D109) -> 613417 | E111: =SUM(E98:E109) -> 651436.23 | F111: =SUM(F98:F109) -> 706405.53 | G111: =SUM(G98:G109) -> 764730.77 | H111: =SUM(H98:H109) -> 826592.48 | I111: =SUM(I98:I109) -> 892180.28
B113: Payments of Employee EOSB | C113: -14121 | D113: -11092 | E113: =E234 -> -11460.69 | F113: =F234 -> -11826.286 | G113: =G234 -> -12203.545 | H113: =H234 -> -12592.838 | I113: =I234 -> -12994.549
B114: Income tax, zakat paid | C114: -14898 | D114: -18416 | E114: =E30 -> -43683.552 | F114: =F30 -> -50787.318 | G114: =G30 -> -57141.95 | H114: =H30 -> -64441.303 | I114: =I30 -> -72533.428
B116: Changes in WC:
B117: Trade and other Receivables | C117: -8235 | D117: -20272 | E117: =-(E222-D222) -> -8271.1411 | F117: =-(F222-E222) -> -9659.9082 | G117: =-(G222-F222) -> -10251.365 | H117: =-(H222-G222) -> -10874.682 | I117: =-(I222-H222) -> -11531.462
B118: Due from related parties | C118: 41 | D118: 30 | E118: =D53-E53 -> 0 | F118: =E53-F53 -> 0 | G118: =F53-G53 -> 0 | H118: =G53-H53 -> 0 | I118: =H53-I53 -> 0
B119: Inventory | C119: 10974 | D119: -19551 | E119: =-(E51-D51) -> -10382.58 | F119: =-(F51-E51) -> -14102.893 | G119: =-(G51-F51) -> -14966.384 | H119: =-(H51-G51) -> -15876.39 | I119: =-(I51-H51) -> -16835.25
B120: Due to related parties | C120: -2487 | D120: 2734 | E120: =E73-D73 -> 0 | F120: =F73-E73 -> 0 | G120: =G73-F73 -> 0 | H120: =H73-G73 -> 0 | I120: =I73-H73 -> 0
B121: Trade and other payables, other liabilities and taxes | C121: -38200 | D121: 42147 | E121: =E72-D72 -> 43409.645 | F121: =F72-E72 -> 43361.299 | G121: =G72-F72 -> 46016.223 | H121: =H72-G72 -> 48814.162 | I121: =I72-H72 -> 51762.311
B123: Net Cash from Operating Activities | C123: =SUM(C111,C113,C114,C117:C121) -> 432801 | D123: =SUM(D111,D113,D114,D117:D121) -> 588997 | E123: =SUM(E111,E113,E114,E117:E121) -> 621047.91 | F123: =SUM(F111,F113,F114,F117:F121) -> 663390.43 | G123: =SUM(G111,G113,G114,G117:G121) -> 716183.75 | H123: =SUM(H111,H113,H114,H117:H121) -> 771621.43 | I123: =SUM(I111,I113,I114,I117:I121) -> 830047.9
B125: Cash Flow from Investing Activities
B127: (Increase) / decrease in term deposits with original maturity of more than three months | C127: 82238 | D127: -49346 | E127: 0 | F127: =(E54+E46)-(F46+F54) -> 0 | G127: =(F54+F46)-(G46+G54) -> 0 | H127: =(G54+G46)-(H46+H54) -> 0 | I127: =(H54+H46)-(I46+I54) -> 0
B128: Purchase of property and equipment | C128: =-C159 -> -106606 | D128: =-D159 -> -94881 | E128: =-E159 -> -122751.71 | F128: =-F159 -> -133214.22 | G128: =-G159 -> -144317.33 | H128: =-H159 -> -156095.55 | I128: =-I159 -> -168585.11
B129: Proceeds from sale of property and equipment | C129: 2441 | D129: 1222 | E129: =Assumptions!J107 -> 1700 | F129: =Assumptions!K107 -> 1700 | G129: =Assumptions!L107 -> 1700 | H129: =Assumptions!M107 -> 1700 | I129: =Assumptions!N107 -> 1700
...

Sheet LBO Model
B2: Sources and Uses - Americana Restaurants LBO
B4: Assumptions
B5: Current Share Price in AED | C5: 1.87 | D5: 46131
B6: Tender Price in AED (ex-dividend) | C6: ='Returns Analysis - LBO'!C17 -> 2.5318601
B7: AED/USD exchange rate | C7: 3.6725
B8: Shares Outstanding | C8: 8398633100
B9: Adeptio current ownership | C9: 0.6603
B10: Float to be acquired | C10: =100%-C9 -> 0.3397
B11: Max. Total Debt/EBITDA | C11: 4
B12: Lease/EBITDA | C12: ='3- Statement Model'!D185/'3- Statement Model'!D14 -> 1.070285
B13: Max LBO Debt/EBITDA | C13: =C11-C12 -> 2.929715
B14: Transaction costs | C14: 0.02
B15: Interest rate | C15: 0.085
B16: Annual amortisation rate | C16: 0.01
B17: Min. operating cash retained ($ 000s) | C17: 80000
B18: FY25 EBITDA (actuals in $ 000s) | C18: =('3- Statement Model'!D14) -> 595604
B19: FY26 EBITDA (projected in $ 000s) | C19: ='3- Statement Model'!E14 -> 638053.71
B20: Tax Rate | C20: =Assumptions!J38 -> 0.16
B22: Derived Calculations
B23: Tender price in USD (cum-dividend) | C23: ='Returns Analysis - LBO'!C15/$C$7 -> 0.71341048
B24: Dividend per share in USD (paid in 2026 pre LBO close) | C24: =-'LBO Model'!C41*1000/'LBO Model'!C8 -> 0.023999977
B25: Share Price Ex-dividend | C25: =C23-C24 -> 0.68941051
B26: Float shares to acquire | C26: =$C$8*$C$10 -> 2.8530157e+09
B27: Float acquisition cost ($ 000s) | C27: =$C$26*$C$25/1000 -> 1966899
B28: Transaction costs ($ 000s) | C28: =C27*C14 -> 39337.979
B29: Total gross LBO debt drawable ($ 000s) | C29: =C18*C13 -> 1744950
B30: Net LBO debt drawn ($ 000s) | C30: =MAX(MIN(C29,C27+C28-C45),0) -> 1744950
B31: Adeptio equity required ($ 000s) | C31: =MAX(C27+C28-C30-C45,0) -> 125443.95
B33: Cash Reconciliation - 2025 Closing Balance to LBO Close
C34: ($ in 000s)
B35: ST Deposits available | C35: ='3- Statement Model'!D54 -> 145235
B36: LT Deposits available | C36: ='3- Statement Model'!D46 -> 117838
B37: Cash Balance Available | C37: ='3- Statement Model'!D55 -> 154337
B38: Minimum Cash Balance | C38: =C17 -> 80000
B39: Excess operating cash | C39: =C37-C38 -> 74337
B40: Total cash available | C40: =C35+C36+C39 -> 337410
B41: (-) Dividend payment in 2026 (Pre-LBO close) | C41: =-Assumptions!J104 -> -201567 | D41: [12]
B42: from Cash | C42: =-(MIN(C39,-C41)) -> -74337
B43: from ST Deposits | C43: =-MIN(C35,-(C41-C42)) -> -127230
B44: from LT Deposits | C44: =-MIN(C36,-(C41-C42-C43)) -> 0
B45: Net cash swept | C45: =C40+C41 -> 135843
B47: Balances before LBO Close
B48: ST Deposits | C48: =C35+C43 -> 18005
B49: LT Deposits | C49: =C36+C44 -> 117838
B50: Cash | C50: =C37+C42 -> 80000
B51: Balances post Sweep at LBO Close
B52: ST Deposits | C52: 0
B53: LT Deposits | C53: 0
B54: Cash | C54: =C38 -> 80000
B56: Sources | E56: Uses
B57: Item | C57: $ 000s | D57: % of total | E57: Item | F57: $ 000s | G57: % of total
B58: LBO Debt drawn | C58: =C30 -> 1744950 | D58: =C58/$C$63 -> 0.86976267 | E58: Float Acquisition cost | F58: =C27 -> 1966899 | G58: =F58/$F$63 -> 0.98039216
B59: ST Deposits swept | C59: =C35+C43 -> 18005 | D59: =C59/$C$63 -> 0.0089745132 | E59: Transaction costs | F59: =C28 -> 39337.979 | G59: =F59/$F$63 -> 0.019607843
B60: LT Deposits swept | C60: =C36+C44 -> 117838 | D60: =C60/$C$63 -> 0.058735834
B61: Excess Operating Cash swept | C61: =C39+C42 -> 0 | D61: =C61/$C$63 -> 0
B62: Adeptio equity | C62: =C31 -> 125443.95 | D62: =C62/$C$63 -> 0.062526988
B63: Total Sources | C63: =SUM(C58:C62) -> 2006237 | D63: =SUM(D58:D62) -> 1 | E63: Total Uses | F63: =SUM(F58:F62) -> 2006237 | G63: =SUM(G58:G62) -> 1
B65: Sources = Uses Check | C65: =C63-F63 -> 0
B67: Metrics
B68: Entry EV ($ 000s) | C68: =(C25*C8/1000)+'3- Statement Model'!D185-(C48+C49+C50) -> 6211728.9
B69: Entry EV/EBITDA | C69: =C68/C18 -> 10.429293
B70: LBO Debt/EBITDA | C70: =C30/C18 -> 2.929715
B71: (LBO Debt + Leases) /EBITDA | C71: =(C30+'3- Statement Model'!D185)/'LBO Model'!C18 -> 4
B72: Tender Premium | C72: ='Returns Analysis - LBO'!C18 -> 0.42090847
B74: Debt Schedule
B75: in $ 000s | C75: 2026 | D75: 2027 | E75: 2028 | F75: 2029 | G75: 2030
B77: Term Loan B
B78: Opening Balance | C78: =C58 -> 1744950 | D78: =C87 -> 1671111.7 | E78: =D87 -> 1540756.8 | F78: =E87 -> 1368560.5 | G78: =F87 -> 1146969.7
B79: Gross Interest Expense | C79: =C78*$C$15 -> 148320.75 | D79: =D78*$C$15 -> 142044.5 | E79: =E78*$C$15 -> 130964.33 | F79: =F78*$C$15 -> 116327.65 | G79: =G78*$C$15 -> 97492.421
B80: ="Tax Shield ("&TEXT(C20,"0.0%")&")" -> Tax Shield (16.0%) | C80: =-C79*$C$20 -> -23731.32 | D80: =-D79*$C$20 -> -22727.12 | E80: =-E79*$C$20 -> -20954.293 | F80: =-F79*$C$20 -> -18612.423 | G80: =-G79*$C$20 -> -15598.787
B81: Net Interest (after tax) | C81: =C79+C80 -> 124589.43 | D81: =D79+D80 -> 119317.38 | E81: =E79+E80 -> 110010.04 | F81: =F79+F80 -> 97715.222 | G81: =G79+G80 -> 81893.633
B83: ="Mandatory Amortisation ("&TEXT(C16,"0.0%")&")" -> Mandatory Amortisation (1.0%) | C83: =-C78*$C$16 -> -17449.5 | D83: =-D78*$C$16 -> -16711.117 | E83: =-E78*$C$16 -> -15407.568 | F83: =-F78*$C$16 -> -13685.605 | G83: =-G78*$C$16 -> -11469.697
B84: FCF available for sweep | C84: ='3- Statement Model'!E123+'3- Statement Model'!E136+('3- Statement Model'!E140+'3- Statement Model'!E141+'3- Statement Model'!E142+'3- Statement Model'!E143+'3- Statement Model'!E144+'3- Statement Model'!E145+'3- Statement Model'!E146)-C81+C83 -> 56388.767 | D84: ='3- Statement Model'!F123+'3- Statement Model'!F136+('3- Statement Model'!F140+'3- Statement Model'!F141+'3- Statement Model'!F142+'3- Statement Model'!F143+'3- Statement Model'!F144+'3- Statement Model'!F145+'3- Statement Model'!F146)-D81+D83 -> 113643.8 | E84: ='3- Statement Model'!G123+'3- Statement Model'!G136+('3- Statement Model'!G140+'3- Statement Model'!G141+'3- Statement Model'!G142+'3- Statement Model'!G143+'3- Statement Model'!G144+'3- Statement Model'!G145+'3- Statement Model'!G146)-E81+E83 -> 156788.71 | F84: ='3- Statement Model'!H123+'3- Statement Model'!H136+('3- Statement Model'!H140+'3- Statement Model'!H141+'3- Statement Model'!H142+'3- Statement Model'!H143+'3- Statement Model'!H144+'3- Statement Model'!H145+'3- Statement Model'!H146)-F81+F83 -> 207905.28 | G84: ='3- Statement Model'!I123+'3- Statement Model'!I136+('3- Statement Model'!I140+'3- Statement Model'!I141+'3- Statement Model'!I142+'3- Statement Model'!I143+'3- Statement Model'!I144+'3- Statement Model'!I145+'3- Statement Model'!I146)-G81+G83 -> 266971.4
B85: Cash Sweep | C85: =MIN(MAX(C84,0),C78+C79) -> 56388.767 | D85: =MIN(MAX(D84,0),D78+D79) -> 113643.8 | E85: =MIN(MAX(E84,0),E78+E79) -> 156788.71 | F85: =MIN(MAX(F84,0),F78+F79) -> 207905.28 | G85: =MIN(MAX(G84,0),G78+G79) -> 266971.4
B86: Total debt repaid | C86: =-C83+C85 -> 73838.267 | D86: =-D83+D85 -> 130354.91 | E86: =-E83+E85 -> 172196.28 | F86: =-F83+F85 -> 221590.88 | G86: =-G83+G85 -> 278441.1
B87: Closing Balance | C87: =C78-C86 -> 1671111.7 | D87: =D78-D86 -> 1540756.8 | E87: =E78-E86 -> 1368560.5 | F87: =F78-F86 -> 1146969.7 | G87: =G78-G86 -> 868528.56
B89: Total Debt/EBITDA | C89: =(C87+'3- Statement Model'!E185)/'3- Statement Model'!E14 -> 3.615974 | D89: =(D87+'3- Statement Model'!F185)/'3- Statement Model'!F14 -> 3.1701365 | E89: =(E87+'3- Statement Model'!G185)/'3- Statement Model'!G14 -> 2.712417 | F89: =(F87+'3- Statement Model'!H185)/'3- Statement Model'!H14 -> 2.244099 | G89: =(G87+'3- Statement Model'!I185)/'3- Statement Model'!I14 -> 1.7659114
B90: LBO Debt/EBITDA | C90: =C87/'3- Statement Model'!E14 -> 2.6190769 | D90: =D87/'3- Statement Model'!F14 -> 2.2243052 | E90: =E87/'3- Statement Model'!G14 -> 1.8231086 | F90: =F87/'3- Statement Model'!H14 -> 1.4122066 | G90: =G87/'3- Statement Model'!I14 -> 0.98988225
B91: Interest Coverage (EBITDA/total interest) | C91: ='3- Statement Model'!E14/('LBO Model'!C79+(-'3- Statement Model'!E27)) -> 3.3860274 | D91: ='3- Statement Model'!F14/('LBO Model'!D79+(-'3- Statement Model'!F27)) -> 3.7910267 | E91: ='3- Statement Model'!G14/('LBO Model'!E79+(-'3- Statement Model'!G27)) -> 4.3484333 | F91: ='3- Statement Model'!H14/('LBO Model'!F79+(-'3- Statement Model'!H27)) -> 5.1196789 | G91: ='3- Statement Model'!I14/('LBO Model'!G79+(-'3- Statement Model'!I27)) -> 6.2571976
B93: Cumulative Summary
C94: ($ in 000s)
B95: Total gross interest paid | C95: =SUM(C79:G79) -> 635149.64
B96: Total tax shield | C96: =SUM(C80:G80) -> -101623.94
B97: Total Net Interest | C97: =C95+C96 -> 533525.7
B98: Total Mandatory Amortization | C98: =SUM(C83:G83) -> -74723.487
B99: Total Cash Swept | C99: =SUM(C85:G85) -> 801697.95
B100: Total Debt repaid | C100: =SUM(C86:G86) -> 876421.44
B101: Opening Balance of Debt | C101: =C78 -> 1744950
B102: Closing Balance of Debt in 2030 | C102: =G87 -> 868528.56
B103: % of Debt repaid | C103: =1-(C102/C101) -> 0.50226164

Sheet Returns Analysis - LBO
D1: v3.0 April 2026
B2: Returns Analysis - Americana Restaurants LBO
B4: Entry Assumptions
B5: Entry EV ($ 000s) | C5: ='LBO Model'!C68 -> 6211728.9
B6: Entry EBITDA - 2025 ($ 000s) | C6: ='LBO Model'!C18 -> 595604
B7: Entry EV/EBITDA | C7: =C5/C6 -> 10.429293
B8: LBO Debt at Entry ($ 000s) | C8: ='LBO Model'!C30 -> 1744950
B9: Excess cash swept at LBO Entry | C9: ='LBO Model'!C45 -> 135843
B10: Adeptio Equity contribution ($ 000s) | C10: ='LBO Model'!C31 -> 125443.95
B11: Adeptio Initial acquisition equity cost (Oct 2016) ($ 000s) | C11: 850000 | D11: [13]
B12: Adeptio MTO equity cost (Jan 2017) ($ 000s) | C12: 1020000 | D12: [14]
B13: IPO Proceeds (Dec 2022) | C13: 1800000 | D13: [15]
B14: Adeptio Existing Stake | C14: ='LBO Model'!C9 -> 0.6603
B15: Offer price (total consideration) | C15: 2.62 | D15: [16]
B16: Dividend per share in AED (paid pre-close) | C16: =-'LBO Model'!C41*1000*'LBO Model'!C7/'LBO Model'!C8 -> 0.088139915
B17: Tender Price in AED (ex-dividend) | C17: =C15-C16 -> 2.5318601
B18: Tender Premium to market | C18: =(C17-('LBO Model'!C5-C16))/('LBO Model'!C5-C16) -> 0.42090847
B20: Exit Assumptions
B21: Exit year | C21: 2030
B22: Growth rate scenario | C22: =IFERROR(CHOOSE(Assumptions!E2,"Bear","Base","Bull"),"Base") -> Base
B23: Exit EBITDA ($ 000s) | C23: ='3- Statement Model'!I14 -> 877405.93
B24: Exit EV/EBITDA ($ 000s) | C24: 8.09
B25: LBO Debt at exit ($ 000s) | C25: ='LBO Model'!C102 -> 868528.56
B26: Lease Liabilitiies at exit ($ 000s) | C26: ='3- Statement Model'!I185 -> 680892.57
B27: Minimum Cash Retained ($ 000s) | C27: ='LBO Model'!C17 -> 80000
B29: Incremental IRR Returns - LBO vs Hold Listed
B31: Incremental IRR | C31: =XIRR(F98:F103,C98:C103,) -> 0.065586129
B33: Entry and Exit Equity Value Summary
C34: ($ in 000s)
B36: Entry EV | C36: ='LBO Model'!C68 -> 6211728.9
B37: (-) Lease Liabilities at entry | C37: =-'3- Statement Model'!E180 -> -637466
B38: (+) Cash at entry | C38: =SUM('LBO Model'!C48:C50) -> 215843
B39: Implied Opening Equity | C39: =C36+C37+C38 -> 5790105.9
B40: Adeptio's stake in Opening Equity | C40: =C39*'LBO Model'!C9 -> 3823206.9
B41: Equity investment at LBO entry | C41: =C10 -> 125443.95
B42: Equity Base at LBO entry | C42: =C40+C41 -> 3948650.9
B44: Exit EV | C44: =C24*C23 -> 7098214
B45: (-) LBO Debt at exit | C45: =-'LBO Model'!G87 -> -868528.56
B46: (-) Lease Liabilities at exit | C46: =-'3- Statement Model'!I185 -> -680892.57
B47: (+) Cash at exit | C47: =C27 -> 80000
B48: Exit Equity to Adeptio | C48: =C44+C45+C46+C47 -> 5628792.9
B50: Post-LBO Returns Waterfall
B51: $ 000s | C51: LBO | D51: Hold-Listed | E51: Incremental
B53: Entry Equity Value of existing equity stake in company at LBO close | C53: ='LBO Model'!$C$25*('LBO Model'!$C$8/1000)*'LBO Model'!$C$9 -> 3823206.9 | D53: ='LBO Model'!$C$25*('LBO Model'!$C$8/1000)*'LBO Model'!$C$9 -> 3823206.9 | E53: =C53-D53 -> 0
B55: LBO Entry
B56: Acquisition of Float | C56: ='LBO Model'!$C$25*('LBO Model'!$C$8/1000)*(1-'LBO Model'!$C$9) -> 1966899 | D56: 0 | E56: =C56-D56 -> 1966899
B57: Loading of Debt in Capital Structure | C57: =-C8 -> -1744950 | D57: 0 | E57: =C57-D57 -> -1744950
B58: Excess cash swept at entry | C58: =-C9 -> -135843 | D58: 0 | E58: =C58-D58 -> -135843
B59: (-) Equity Invested by Adeptio to acquire float | C59: =D98 -> -125443.95 | D59: 0 | E59: =C59-D59 -> -125443.95
B60: Changes in Equity Value due to LBO Entry | C60: =C56+C57+C58+C59 -> -39337.979 | D60: =D56+D57+D58+D59 -> 0 | E60: =C60-D60 -> -39337.979 | F60: [17]
B62: Holding Period
B63: Stake in company held by Adeptio | C63: 1 | D63: =C14 -> 0.6603 | E63: =C63-D63 -> 0.3397
B64: + EBITDA Growth Contribution | C64: =(($C$23-$C$6)*$C$7)*C63 -> 2938995 | D64: =(($C$23-$C$6)*$C$7)*D63 -> 1940618.4 | E64: =C64-D64 -> 998376.61
B65: + Multiple Expansion | C65: =(($C$24-$C$7)*$C$23)*C63 -> -2052510 | D65: =(($C$24-$C$7)*$C$23)*D63 -> -1355272.3 | E65: =C65-D65 -> -697237.63
B66: (-) Lease Liability Movement | C66: =('3- Statement Model'!$E$180-'3- Statement Model'!$I$185)*C63 -> -43426.569 | D66: =('3- Statement Model'!$E$180-'3- Statement Model'!$I$185)*D63 -> -28674.563 | E66: =C66-D66 -> -14752.005
B67: + Net Debt Paydown Benefit | C67: =(C8-C25)*C63 -> 876421.44 | D67: 0 | E67: =C67-D67 -> 876421.44
B68: + Increase in Cash Balances | C68: =('LBO Model'!C54-'LBO Model'!C50)*C63 -> 0 | D68: =('3- Statement Model'!I245-'3- Statement Model'!E240-'3- Statement Model'!E244)*D63 -> 273660.78 | E68: =C68-D68 -> -273660.78
B69: Exit Equity Proceeds | C69: =C53+(C60-C59)+C64+C65+C66+C67+C68 -> 5628792.9 | D69: =D53+(D60-D59)+D64+D65+D66+D67+D68 -> 4653539.2 | E69: =C69-D69 -> 975253.61
B70: + Dividends Received during Holding Period | C70: =SUM(D99:D102) -> 0 | D70: =SUM(E99:E102) -> 710762.41 | E70: =C70-D70 -> -710762.41
B71: Total Equity returns for Adeptio Post LBO | C71: =C69-C53+C70+C59 -> 1680142 | D71: =D69-D53+D70+D59 -> 1541094.7 | E71: =C71-D71 -> 139047.25
B73: Cash Flows Summary Table - LBO vs Hold Listed
C74: LBO (1) | D74: Holding Listed (2) | E74: (1)-(2)
B75: Dividends (2016-2025) | C75: =SUM(D90:D97) -> 782943.84 | D75: =SUM(E90:E97) -> 782943.84 | E75: =C75-D75 -> 0
B76: Dividends (2026-2030) | C76: =SUM(D99:D102) -> 0 | D76: =SUM(E99:E102) -> 710762.41 | E76: =SUM(F99:F102) -> -710762.41
B77: Total Dividends | C77: =C75+C76 -> 782943.84 | D77: =D75+D76 -> 1493706.2 | E77: =E75+E76 -> -710762.41
B78: IPO Proceeds in 2022 | C78: =D89 -> 1800000 | D78: =E89 -> 1800000 | E78: =F89 -> 0
B79: Exit Proceeds 2030E | C79: =D103 -> 5628792.9 | D79: =E103 -> 4653539.2 | E79: =F103 -> 975253.61
B80: Total Proceeds | C80: =SUM(C77:C79) -> 8211736.7 | D80: =SUM(D77:D79) -> 7947245.5 | E80: =SUM(E77:E79) -> 264491.21
B81: Equity Invested | C81: =SUM(D87,D88,D98) -> -1995444 | D81: =SUM(E87,E88) -> -1870000 | E81: =C81-D81 -> -125443.95
B82: Net Cash to Adeptio | C82: =SUM(C80:C81) -> 6216292.7 | D82: =SUM(D80:D81) -> 6077245.5 | E82: =SUM(E80:E81) -> 139047.25
B84: IRR Cash Flow Table - LBO vs Hold Listed
B85: Event | C85: Date | D85: LBO (1) | E85: Holding Listed (2) | F85: Incremental (1)-(2) | G85: [18] | L85: For the Sensitivity Table
B87: Initial acquisition (Oct 2016) | C87: 42663 | D87: =-$C$11 -> -850000 | E87: =-$C$11 -> -850000 | F87: =D87-E87 -> 0 | L87: =D87 -> -850000 | M87: =F87 -> 0
B88: MTO acquisition (Jan 2017) | C88: 42750 | D88: =-$C$12 -> -1020000 | E88: =-$C$12 -> -1020000 | F88: =D88-E88 -> 0 | L88: =D88 -> -1020000 | M88: =F88 -> 0
B89: IPO proceeds (Dec 2022) | C89: 44907 | D89: =$C$13 -> 1800000 | E89: =$C$13 -> 1800000 | F89: =D89-E89 -> 0 | L89: =D89 -> 1800000 | M89: =F89 -> 0
B90: Dividend for 2018 | C90: 43600 | D90: 105941 | E90: =D90 -> 105941 | F90: =D90-E90 -> 0 | L90: =D90 -> 105941 | M90: =F90 -> 0
B91: Dividend for 2019 | C91: 43966 | D91: 59949 | E91: =D91 -> 59949 | F91: =D91-E91 -> 0 | L91: =D91 -> 59949 | M91: =F91 -> 0
B92: Dividend for 2020 | C92: 44331 | D92: 129817 | E92: =D92 -> 129817 | F92: =D92-E92 -> 0 | L92: =D92 -> 129817 | M92: =F92 -> 0
B93: Dividend for 2021 | C93: 44696 | D93: 83089 | E93: =D93 -> 83089 | F93: =D93-E93 -> 0 | L93: =D93 -> 83089 | M93: =F93 -> 0
B94: Dividend for 2022 | C94: 45061 | D94: =103500*66.03% -> 68341.05 | E94: =D94 -> 68341.05 | F94: =D94-E94 -> 0 | L94: =D94 -> 68341.05 | M94: =F94 -> 0
B95: Dividend for 2023 | C95: 45427 | D95: =180000*66.03% -> 118854 | E95: =D95 -> 118854 | F95: =D95-E95 -> 0 | L95: =D95 -> 118854 | M95: =F95 -> 0
B96: Dividend for 2024 | C96: 45792 | D96: =127000*66.03% -> 83858.1 | E96: =D96 -> 83858.1 | F96: =D96-E96 -> 0 | L96: =D96 -> 83858.1 | M96: =F96 -> 0
B97: Dividend for 2025 | C97: 46157 | D97: =Assumptions!J104*C14 -> 133094.69 | E97: =D97 -> 133094.69 | F97: =D97-E97 -> 0 | L97: =D97 -> 133094.69 | M97: =F97 -> 0
B98: LBO entry equity | C98: 46188 | D98: =-'LBO Model'!C62 -> -125443.95 | E98: 0 | F98: =IF(D98-E98<>0,D98-E98,-0.00000001) -> -125443.95 | L98: =D98 -> -125443.95 | M98: =F98 -> -125443.95
B99: Dividend for 2026 | C99: 46522 | D99: ='3- Statement Model'!F140 -> 0 | E99: =-'3- Statement Model'!F$244*C14 -> 144623.7 | F99: =D99-E99 -> -144623.7 | L99: =D99 -> 0 | M99: =F99 -> -144623.7
B100: Dividend for 2027 | C100: 46888 | D100: ='3- Statement Model'!G$140 -> 0 | E100: =-'3- Statement Model'!G$244*C14 -> 167004.22 | F100: =D100-E100 -> -167004.22 | L100: =D100 -> 0 | M100: =F100 -> -167004.22
B101: Dividend for 2028 | C101: 47253 | D101: ='3- Statement Model'!H$140 -> 0 | E101: =-'3- Statement Model'!H$244*C14 -> 187729.4 | F101: =D101-E101 -> -187729.4 | L101: =D101 -> 0 | M101: =F101 -> -187729.4
B102: Dividend for 2029 | C102: 47618 | D102: ='3- Statement Model'!I$140 -> 0 | E102: =-'3- Statement Model'!I$244*C14 -> 211405.08 | F102: =D102-E102 -> -211405.08 | L102: =D102 -> 0 | M102: =F102 -> -211405.08
B103: Exit equity proceeds (2030E) | C103: 47848 | D103: =($C$23*$C$24)-($C$25)+$C$27-$C$26 -> 5628792.9 | E103: =((($C$23*$C$24)+'3- Statement Model'!$I$245)-$C$26)*$C$14 -> 4653539.2 | F103: =D103-E103 -> 975253.61 | L103: =(M104*$C$24)-($C$25)+$C$27-$C$26 -> 4209150.1 | M103: =((M104*$C$24)-($C$25)+$C$27-$C$26)-((((M104*$C$24)+'3- Statement Model'!$I$245)-$C$26)*$C$14) -> 493000.96
L104: 1 | M104: =CHOOSE(L104,C128,D128,E128,F128,G128) -> 701924.74
B105: IRR Returns - Scenario Summary Table
C106: Bear | D106: Base | E106: Bull
B107: LFL rate | C107: 0.03 | D107: 0.04 | E107: 0.05
B108: NSO | C108: 110 | D108: 125 | E108: 140
B109: Revenue CAGR | C109: 0.0683 | D109: 0.0835 | E109: 0.0987
B110: G&A Expense | C110: 0.085 | D110: 0.07 | E110: 0.065
B111: EBITDA Margin | C111: 0.23 | D111: 0.235 | E111: 0.24
B112: PPE Capex | C112: 0.04 | D112: 0.045 | E112: 0.05
B113: Exit Multiple | C113: 8.09 | D113: 8.09 | E113: 8.09
B114: Incremental XIRR | C114: -0.1498 | D114: 0.0656 | E114: 0.1505
...

Sheet Appendix - Footnotes
C2: Appendix - Footnotes
B4: [1] | C4: Methodology behind Model assumptions
C6: Section | D6: Variable | E6: Basis (Short Note) | F6: Full Methodology
C7: Americana Restaurants LBO Model | All figures in USD 000s unless stated | March 2026
C8: Revenue Drivers
C9: Revenue Drivers | D9: NSO (Organic) | E9: Scenario toggle; base 125, bear 110, bull 140 | F9: Base case of 125 NSOs per annum, in line with the midpoint of management guidance of 120-130. Bear: 110 (below guidance, stress scenario reflecting potential slowdown in expansion); Bull: 140 (above guidance, reflecting accelerated rollout) Management guidance has in the past included acquired stores as a part of NSOs as well, the same methodology has been assumed for 2026
C10: Revenue Drivers | D10: LfL Growth | E10: Scenario toggle; base 4.0%, bear 3.0%, bull 5.0% | F10: Base case of 4.0%, representing the lower end of management guidance of mid single digits (4-6%). Bear: 3.0% (below guidance); Bull: 5.0% (management guidance). 2024 actual of -12.5% and 2025 actual of 9.7% excluded as distorted by regional geopolitical headwinds and subsequent normalisation
C11: Revenue Drivers | D11: Stores Acquired | E11: Actuals only; zero from 2027 | F11: 2025-Pizza Hut Oman; 2026-MAT. Note: MAT stores assumed to reach similar operational efficiency and sales per store levels as the existing stores for simplicity reasons. Current revenue per store for MAT is $2.1m
C12: Operating Expenses
C13: Operating Expenses | D13: COGS (% of Revenue) | E13: Slight improvement from 2025 actual (41.3%) | F13: Slight improvement from the 2025 actual of 41.3% (2024: 42.5%), reflecting management guidance on inventory cost savings through menu reengineering and supplier negotiations. 2022/2023 excluded (2022: 48.3%; 2023: 47.7%) as unrepresentative, reflecting elevated global food commodity prices
C14: Operating Expenses | D14: S&A Expense (% of Revenue) | E14: 2-yr avg (2024: 28.62%; 2025: 28.49%) | F14: Held at the 2-year average of 28.56% (2024: 28.62%; 2025: 28.49%), rounded to 28.5%. 2022/2023 excluded (2022: 31.07%; 2023: 32.21%) as unrepresentative of the current cost structure
C15: Operating Expenses | D15: G&A Expense (% of Revenue) | E15: Scenario toggle; base 7.0%, bear 8.5%, bull 6.5% | F15: Scenario toggle reflecting operating leverage and management guidance on G&A reduction through restructuring and offshoring of low-value-add roles (2022: 8.12%; 2023: 7.95%; 2024: 7.26%; 2025: 6.93%). Bear: 8.5% stress assumption reflecting inability to reduce/worsening of fixed G&A costs in a weaker revenue environment. Base: 7.0% modest improvement from 2024 actual, broadly in line with the observed downward trend. Bull: 6.5% reflects partial realisation of management efficiency initiatives on a larger revenue base
C16: Operating Expenses | D16: EBITDA Margin | E16: Plug; base 23.5%, bear 23.0%, bull 24.0% | F16: Plug derived as revenue less COGS, S&A and G&A. Base case of 23.5% is in line with the 2025 outturn of 23.7% and consistent with management guidance of margins in line with 2025.
C17: Financing and Tax
C18: Financing and Tax | D18: Effective Income Tax Rate | E18: 16% - Pillar 2 full implementation | F18: Forecast at 16%, reflecting the full implementation of the OECD Pillar 2 global minimum tax rate. Historical effective rates of 12.0% (2024) and 14.0% (2025) were below 15% prior to full Pillar 2 implementation
C19: Financing and Tax | D19: Finance Income [LBO] | E19: Zero - cash swept at LBO entry | F19: Excess cash and deposits swept at LBO entry. Interest income is likely to be immaterial
C20: Financing and Tax | D20: Finance Income (% of Opening Cash) [Hold-Listed Scenario] | E20: 4.0% on opening cash - below 2-yr avg (4.98%) | F20: Interest income on cash reserves assumed at 4.0% per annum, below the 2-year historical average of 4.98% (2024: 5.60%; 2025: 4.35%), reflecting the declining interest rate environment over the forecast period
C21: Financing and Tax | D21: Lease Finance Costs | E21: 6.3% - 3-yr avg adjusted upward for IBR increases | F21: Historical average (2023-2025) of 6.15% adjusted upwards to reflect the increase in lease IBRs. 2025 rates expected to reverse partially as the Fed cuts rates. (2022: 5.21%; 2023: 5.78%; 2024: 5.95%; 2025: 6.72%)
C22: Financing and Tax | D22: Non-Lease Finance Costs | E22: Frozen at 2025 actual ($42k) - bank charges only | F22: Consists of bank charges. Bank charges frozen due to lack of identifiable drivers
C23: Working Capital
C24: Inventory | D24: Inventory Days | E24: Anchored to 2025 actual (54.6 days) | F24: Anchored to the 2025 actual of 54.6 days. Consistent with 2022 and 2024 outturns of 55.3 and 52.6 days respectively. 2023 excluded as an outlier year of apparent destocking (49.3 days)
C25: Trade and Other Receivables | D25: AR Days | E25: Anchored to 2025 actual (7.5 days) | F25: Anchored to the 2025 actual of 7.52 days. Consistent with the observed upward trend (2022: 4.3 days to 2025: 7.5 days)
C26: Trade and Other Receivables | D26: Prepaid Expenses (% of Revenue) | E26: 3-yr avg 1.61% (2023-2025); rounded to 1.5% | F26: 3-year average of 1.61% of revenue (2023: 1.64%; 2024: 1.66%; 2025: 1.52%), rounded down to 1.5% which is consistent with 2025 actuals. 2022 excluded (1.31%) as unrepresentative of the current prepaid expense base
C27: Trade and Other Receivables | D27: Advances to Suppliers | E27: Frozen at 2025 actual ($1,612k) - immaterial | F27: Held at 2025 closing balance due to lack of identifiable drivers. Will vary based on vendor negotiation. Immaterial
C28: Trade and Other Receivables | D28: Refundable Deposits | E28: Frozen at 2025 actual ($16,100k) | F28: Held at 2025 closing balance. Theoretically should grow with store count, however individual deposits will vary significantly by market and landlord. Immaterial at less than 1% of revenue
C29: Trade and Other Receivables | D29: Accrued Income (% of Revenue) | E29: 3-yr avg 0.59% (2023-2025); rounded to 0.6% | F29: 3-year average of 0.59% of revenue (2023: 0.51%; 2024: 0.63%; 2025: 0.61%), rounded to 0.6%. 2022 excluded (0.24%) as unrepresentative of the current franchise and delivery partner mix
C30: Trade and Other Receivables | D30: Insurance Receivables | E30: Frozen at 2025 actual ($410k) - immaterial | F30: Held at 2025 closing balance. Timing driven balance with no clear predictable forward driver. Immaterial
C31: Trade and Other Receivables | D31: Staff Receivables | E31: Frozen at 2025 actual ($2,553k) - immaterial | F31: Held at 2025 closing balance. Driven by HR policy. Immaterial
C32: Trade and Other Receivables | D32: VAT Receivable | E32: Frozen at 2025 actual ($4,558k) - immaterial | F32: Held at 2025 closing balance. Recovery timing varies across jurisdictions. No reliable driver given presence in multiple markets. Immaterial
C33: Trade and Other Receivables | D33: Other Receivables | E33: Frozen at 2025 actual ($8,494k) - immaterial | F33: Residuals with no single identifiable driver. Immaterial
C34: Trade and Other Receivables | D34: Non-Current Receivables Portion | E34: Frozen at $7,500k - 2023/2024 avg | F34: Data available only post 2023, frozen value reflects 2023 and 2024 levels. Spike in 2025 considered timing-driven and not structural
C35: Trade and Other Payables | D35: Trade Payables (% of Revenue) | E35: 2-yr avg 18.65% (2024: 18.75%; 2025: 18.55%) | F35: 2-year average of 18.65% of revenue (2024: 18.75%; 2025: 18.55%). Downward trend from 2022/2023 levels considered structural rather than cyclical (2022: 19.06%; 2023: 19.50%)
C36: Trade and Other Payables | D36: Non-Current Trade Payables | E36: Frozen at 2025 actual ($2,729k) - immaterial | F36: Held at 2025 closing balance. Represents unamortised supplier volume discounts deducted from inventory cost and recognised through COGS. Immaterial
C37: Fixed Assets
C38: PPE | D38: PPE Capex (% of Revenue) | E38: Scenario toggle; base 4.5%, bear 4.0%, bull 5.0% | F38: Scenario toggle. Base case of 4.5% represents the midpoint between the 2025 actual of 3.78% (113 organic NSOs) and the 4-year average of 4.74% (2022: 5.05%; 2023: 5.29%; 2024: 4.85%; 2025: 3.78%). Bear case of 4.0% anchored to the 2025 actual, reflecting a cautious expansion environment. Bull case of 5.0% consistent with the 4-year average, reflecting accelerated store rollout at 140 NSOs
C39: PPE | D39: PPE Disposals | E39: Frozen at 2025 actual ($2,691k) - immaterial | F39: Frozen, immaterial and would add unnecessary complexity to model
C40: PPE | D40: PPE Depreciation (% of Opening Balance) | E40: 4-yr avg 25.9% (2022-2025); rounded to 26.0% | F40: 4-year average of 25.9% of opening PPE balance (2022: 26.7%; 2023: 25.6%; 2024: 24.9%; 2025: 26.4%). Rounded to 26.0%.
C41: PPE | D41: PPE Other Adjustments | E41: Zero - hyperinflation/FX, non-operating | F41: Due to Hyperinflation and Forex movements which are of a non-operating nature. Assumed to be zero
C42: RoU Assets | D42: RoU Addition per NSO | E42: 2-yr avg $2,031k/store; rounded to $2,000k | F42: 2-year average of $2,031k per organic NSO (2024: $1,803k; 2025: $2,258k), rounded to $2,000k. 2022/2023 excluded (2022: $1,344k; 2023: $1,069k) as unrepresentative, reflecting a lower IBR and rental cost environment
C43: RoU Assets | D43: RoU Depreciation (% of Opening Balance) | E43: 2-yr avg 36.59% (2024-2025); rounded to 36.0% | F43: 2-year average of 36.59% of opening RoU NBV (2024: 36.87%; 2025: 36.32%), rounded to 36.0%. 2022/2023 excluded (2022: 42.20%; 2023: 41.36%) as unrepresentative, reflecting a portfolio with shorter average remaining lease terms
C44: RoU Assets | D44: RoU Terminations | E44: Frozen at 2025 actual ($7,179k) | F44: RoU asset terminations held constant at the 2025 actual of $7,179k per annum. No reliable driver identified as terminations reflect opportunistic lease exits and store closures which are not predictable from store count or expansion assumptions.
C45: Balance Sheet - Lease Liability | D45: Lease Liability Additions/Terminations | E45: Equal to RoU asset movements - see RoU assumptions | F45: Additions and Terminations equal to RoU asset movements. See RoU assumptions above
C46: Balance Sheet - Lease Liability | D46: Lease Principal Payment (% of Opening Balance) | E46: 3-yr avg 36.2% (2023-2025); rounded to 35.0% | F46: 3-year average of 36.2% of opening lease liability (2023: 39.9%; 2024: 35.4%; 2025: 33.2%). Downward trend reflects portfolio maturation as longer-dated leases are added. 35% adopted, broadly in line with the 3-year average and conservative relative to the 2025 outturn of 33.2%
C47: Balance Sheet - Lease Liability | D47: Lease Current/Non-Current Split | E47: Frozen at 33.0% - 3-yr avg (2023-2025: 32.7%) | F47: Held at 33.0%, in line with the 3-year average of 32.7% (2023: 32.7%; 2024: 32.7%; 2025: 32.7%). 2022 excluded as an outlier at 36.8%, reflecting a different portfolio composition in an earlier stage of expansion
C48: Investment Property | D48: Investment Property | E48: Frozen at 2025 actual ($3,712k) - immaterial | F48: Held constant at 2025 level. Movements are immaterial.
C49: Intangibles | D49: Intangibles Capex (% of Revenue) | E49: 4-yr avg 0.59%; rounded to 0.6% | F49: 4-year average of 0.59% of revenue (2022: 0.34%; 2023: 0.76%; 2024: 0.78%; 2025: 0.49%), rounded to 0.6%. No discernible trend; average adopted as the most appropriate anchor.
... C53: Intangibles | D53: MAT Franchise Rights - Amortisation | E53: 1.33% p.a. over 75-yr exclusive franchise term | F53: 2026 amortisation of $231k calculated on acquisition cost of $20,800k for 10 months (March to December). From 2027 onwards, amortisation calculated as 1.33% of opening MAT franchise rights balance
C54: Other Balance Sheet Items
C55: Deferred Tax Asset | D55: Deferred Tax Asset | E55: Frozen at 2025 actual ($3,594k) - immaterial | F55: Held at 2025 closing balance. Cannot be reliably estimated without tax base data. Immaterial
C56: Deferred Tax Liabilities | D56: Deferred Tax Liabilities | E56: Frozen at 2025 actual ($2,110k) - immaterial | F56: Held at 2025 closing balance. Cannot be reliably estimated without tax base data. Immaterial
C57: Income Tax / Zakat Payable | D57: Income Tax / Zakat Payable | E57: Frozen at 2025 actual ($36,745k) - timing driven | F57: Held at 2025 closing balance. Mainly driven by timing.
C58: Due to Related Parties | D58: Due to Related Parties | E58: Frozen at 2025 actual ($16,681k) | F58: Held at 2025 closing balance. Mainly represents trading payables to related food suppliers. Balances expected to persist post LBO
C59: Provisions (Legal/Tax/Other) | D59: Provisions (Legal/Tax/Other) | E59: Frozen at 2025 actual ($15,077k) - event-driven | F59: Held at 2025 closing balance. Event-driven with no reliable operational driver
C60: Equity | D60: Other Reserves | E60: Frozen at post-LBO Day 1 balance | F60: Held at post LBO closing balance. Comprises forex translation which isn't reliably predictable. On Day 1 of LBO, Share based payment reserve of $2976k zeroed out and transferred to retained earnings upon cancellation of existing schemes.
C61: Equity | D61: NCI (Non-Controlling Interest) | E61: Frozen at 2025 actual ($984k) - residual | F61: Held at 2025 closing balance. Reduction from 2024 to 2025 reflects acquisition of additional shares in subsidiary. Residual is immaterial
C62: Provision for End of Service Benefits
C63: EOSB | D63: EOSB Interest (% of Opening Balance) | E63: 3-yr avg 4.69% (2023-2025); 2022 excluded (outlier) | F63: Anchored to 3 year average of 4.69% (2023: 4.50%; 2024: 4.86%; 2025: 4.72%). 2022 excluded as an outlier (1.54%)
C64: EOSB | D64: EOSB Service Charge (% of Opening Balance) | E64: 3-yr avg 14.7% (2023-2025); 2022 excluded (outlier) | F64: 3-year average of 14.7% of opening EOSB liability (2023: 14.6%; 2024: 14.9%; 2025: 14.5%). 2022 excluded as an outlier (11.2%) reflecting a different discount rate environment.
C65: EOSB | D65: EOSB Payments (% of Opening Balance) | E65: 2025 actual 16.2%; 2024 excluded (elevated) | F65: 2024 excluded as elevated, likely reflecting higher staff turnover during a period of significant revenue decline driven by regional geopolitical headwinds. 2025 outturn of 16.2% adopted as representative
C66: Cash Flow Statement Items
C67: Dividends Paid (LBO Scenario) | D67: Dividends Paid (LBO Scenario) | E67: Zero post-LBO; 2026 pre-close dividend $201,567k | F67: Suspended post LBO as excess cash swept to service debt. Dividend paid in 2026 on 2025 NP (declared in Feb 2026) likely to occur before LBO close
C68: Dividend Payout Ratio (Hold-Listed Scenario) | D68: Dividend Payout Ratio (Hold-Listed Scenario) | E68: 90% of prior year NP - 2-yr avg (2024: 84%; 2025: 92%) | F68: Dividends in the Hold Listed scenario are projected at 90% of prior year net profit, consistent with the company's established high dividend distribution policy. The assumption is anchored to the 2-year average payout ratio of 88% (2024: 84% being $127,000k on net profit of $151,404k; 2025: 92% being approximately $201,300k on net profit of $218,450k). The company's stated minimum dividend policy is 50% of net profit; however, historical payouts have consistently and materially exceeded this floor. A 90% assumption is considered appropriate for the forecast period as it reflects the company's demonstrated commitment to returning cash to shareholders while remaining marginally below the most recent 2025 outturn of 92%
C69: Key Money Paid | D69: Key Money Paid | E69: 2-yr avg $1,092k (2024: $504k; 2025: $1,680k) | F69: 2-year average of $1,092k (2024: $504k; 2025: $1,680k), rounded up to $1,100k. 2022 and 2023 excluded as unrepresentative
C70: Proceeds from PPE Disposal | D70: Proceeds from PPE Disposal | E70: 3-yr avg $1,720k; rounded to $1,700k | F70: 3-year average of $1,720k, rounded down. 2022 excluded as an outlier. No discernible trend overall. average adopted as the most appropriate anchor
C71: Acquisition of Subsidiary | D71: Acquisition of Subsidiary | E71: 2026 only: $20,830k - MAT acquisition | F71: Represents consideration paid for the acquisition of 100% stake in Yummy Junction International Investment LLC and Rock Star International Restaurant For Meals Serving LLC, operating under the brand name Malak Al Tawouk (MAT), for a total consideration of $20,830k. The acquisition, completed in February 2026, is intended to be funded through the Group's internal cash reserves with no external financing required
C72: General Model Notes
C73: Note | D73: Detail
C74: Tax Paid vs Tax Recognised | D74: Tax paid assumed equal to the full income tax charge for the year. Timing differences between tax recognised and tax paid not modelled given the complexity of operating across 12 tax jurisdictions
C75: Non-Lease Finance Costs - P&L Composition | D75: Non-Lease Finance Costs in the P&L also includes EOSB Interest. EOSB interest is addressed in the assumptions relating to EOSB above
C76: Historical Data Exclusions - General Principle | D76: Where historical years are excluded from averages, this reflects distortion from: (i) post-COVID recovery (2022/2023 for certain metrics); (ii) hyperinflationary or geopolitical impacts; or (iii) one-off structural changes. Exclusion rationale is documented on a line-by-line basis in the notes above.
B78: =Assumptions!Q34 -> [2] | C78: Finance Income (% of opening Cash) [Hold Listed Scenario]
C79: In the Hold Listed scenario, Adeptio retains its existing stake in AMR without executing the LBO. As a result, the company's cash reserves are not swept to repay acquisition debt and accumulate over the forecast period. This generates material interest income which increases net profit, in turn increasing dividends distributed to Adeptio under the 70% payout assumption. A separate Hold Listed cash roll forward has been constructed to capture this compounding effect, as using the LBO model cash balance would materially understate the Hold Listed scenario's cash position and consequently overstate the IRR uplift from the LBO. The interest rate assumption of 4.0% is applied to the opening cash balance each year.
B81: ='3- Statement Model'!J12 -> [3] | C81: Other Income
C82: This includes Loss on disposal of PPE and intangibles.
B84: ='3- Statement Model'!J46 -> [4] | C84: Long term Deposits with Banks
C85: Deposits utilised to pay dividend pre-LBO close. Balances swept at LBO entry. Refer to 'LBO Model' sheet for cash reconciliation
B87: ='3- Statement Model'!J54 -> [5] | C87: Short term Deposits with Banks
C88: Deposits utilised to pay dividend pre-LBO close. Balances swept at LBO entry. Refer to 'LBO Model' sheet for cash reconciliation
B90: ='3- Statement Model'!J140 -> [6] | C90: Dividends paid to shareholders
C91: Dividend paid ($201,567) pre-LBO close from deposits and cash balances and does not reflect in post LBO CFS.
B93: ='3- Statement Model'!J153 -> [7] | C93: Cash and cash equivalents at the end of the year (As shown in the Cash Flow Statement)
C94: Cash balance reflects the standalone operational model and does not incorporate LBO debt sweep mechanics. In the LBO model, excess cash above the minimum operating balance of $80,000k is swept to repay debt annually. Refer to the debt schedule on the LBO Model sheet.
B96: ='3- Statement Model'!J237 -> [8] | C96: Cash Reconciliation (LBO to Hold-listed)
C97: This roll forward will only affect the XIRR calculation for the Hold-listed scenario (for comparison against LBO returns), and not the LBO model.
B99: ='3- Statement Model'!J240 -> [9] | C99: Opening Cash as per CFS (within the Cash reconciliation schedule)
C100: Closing balance of 2025 used as opening balance for 2026 Hold Listed BS.
C101: Cash here includes cash and cash eq., ST and LT deposits
B103: ='3- Statement Model'!J241 -> [10] | C103: Add:Net Cash increase/decrease as per CFS (within the cash reconciliation schedule)
C104: The Hold Listed cash roll forward utilises the net cash flows from the 3-statement model CFS with minimal adjustments. This is appropriate as the 3-statement model is constructed on a standalone operational basis and does not incorporate LBO-specific items. Specifically, LBO debt drawdown, mandatory amortisation, and cash sweep mechanics are modelled exclusively within the LBO Model sheet and do not flow through the 3-statement CFS. The financing section of the CFS reflects only recurring operational financing items, namely lease principal payments, lease interest, and bank charges which are identical under both the LBO and Hold Listed scenarios.
C106: Two adjustments are made to derive the Hold Listed cash position:
C108: (i) interest income of 4.0% per annum is applied to the opening cash balance each year, reflecting returns on accumulated cash reserves, compared to zero in the LBO scenario where deposits are swept at entry; and
C109: (ii) dividends of 90% of revised net profit (inclusive of after-tax interest income) are deducted annually, as Adeptio would continue to receive distributions as a listed shareholder.
C111: All other CFS line items are assumed identical across both scenarios.
B113: ='3- Statement Model'!J244 -> [11] | C113: Dividends on Revised Net Profits of prior year
C114: Payment of dividend usually has historically occurred around May of each year. This dividend corresponds to the profits earned the previous year
B116: ='LBO Model'!D41 -> [12] | C116: Dividend payment in 2026 (Pre-LBO close)
C117: It has been assumed that for the payment of this dividend, cash is utilised first, then ST deposits, and if any balance still remains, LT deposits.
B119: ='Returns Analysis - LBO'!D11 -> [13] | C119: Adeptio Initial acquisition equity cost (Oct 2016) ($ 000s)
C120: $1.5 billion was financed using debt, total value of deal was $2.35b
B122: ='Returns Analysis - LBO'!D12 -> [14] | C122: Adeptio MTO equity cost (Jan 2017) ($ 000s)
...

Sheet WACC Working
B2: 1 - Segment revenues (2025)
B3: Segment | C3: Revenue
B4: Major GCC | C4: 1821532
B5: Lower GCC | C5: 225978
B6: Northern Africa | C6: 223236
B7: Others | C7: 238075
B8: Total | C8: =SUM(C4:C7) -> 2508821
B10: 2 - Revenue Allocation using store counts as proxy
B11: Country | C11: Stores | D11: Weighted Revenue | E11: Region
B12: UAE | C12: 652 | D12: =(C12/SUM($C$12:$C$14))*$C$4 -> 701085.52 | E12: Major GCC
B13: KSA | C13: 766 | D13: =(C13/SUM($C$12:$C$14))*$C$4 -> 823667.95 | E13: Major GCC
B14: Kuwait | C14: 276 | D14: =(C14/SUM($C$12:$C$14))*$C$4 -> 296778.53 | E14: Major GCC
B15: Oman | C15: 101 | D15: =(C15/SUM($C$15:$C$17))*$C$5 -> 79525.359 | E15: Lower GCC
B16: Bahrain | C16: 77 | D16: =(C16/SUM($C$15:$C$17))*$C$5 -> 60628.244 | E16: Lower GCC
B17: Qatar | C17: 109 | D17: =(C17/SUM($C$15:$C$17))*$C$5 -> 85824.397 | E17: Lower GCC
B18: Egypt | C18: 450 | D18: =(C18/SUM($C$18:$C$19))*$C$6 -> 198923.17 | E18: Northern Africa
B19: Morocco | C19: 55 | D19: =(C19/SUM($C$18:$C$19))*$C$6 -> 24312.832 | E19: Northern Africa
B20: Lebanon | C20: 17 | D20: =(C20/SUM($C$20:$C$23))*$C$7 -> 15388.878 | E20: Others
B21: Kazakhstan | C21: 147 | D21: =(C21/SUM($C$20:$C$23))*$C$7 -> 133068.54 | E21: Others
B22: Jordan | C22: 57 | D22: =(C22/SUM($C$20:$C$23))*$C$7 -> 51598.004 | E22: Others
B23: Iraq | C23: 42 | D23: =(C23/SUM($C$20:$C$23))*$C$7 -> 38019.582 | E23: Others
B24: Total | C24: =SUM(C12:C23) -> 2749 | D24: =SUM(D12:D23) -> 2508821
B26: 3 - Blended ERP calculation
B27: Country | C27: Old ERP | D27: ERP New | E27: Blended Old ERP (ex-Leb) | F27: Blended New ERP (all) | G27: Blended New ERP (ex-Leb)
B28: UAE | C28: 4.93 | D28: 5.91 | E28: =C28*(D12/($D$24-$D$20)) -> 1.3861823 | F28: =D28*(D12/($D$24)) -> 1.6515389 | G28: =D28*(D12/($D$24-$D$20)) -> 1.6617318
B29: KSA | C29: 5.72 | D29: 6.46 | E29: =C29*(D13/($D$24-$D$20)) -> 1.8895163 | F29: =D29*(D13/($D$24)) -> 2.1208747 | G29: =D29*(D13/($D$24-$D$20)) -> 2.1339642
B30: Kuwait | C30: 5.34 | D30: 6.09 | E30: =C30*(D14/($D$24-$D$20)) -> 0.63558873 | F30: =D30*(D14/($D$24)) -> 0.72041061 | G30: =D30*(D14/($D$24-$D$20)) -> 0.72485681
B31: Oman | C31: 6 | D31: 6.92 | E31: =C31*(D15/($D$24-$D$20)) -> 0.1913636 | F31: =D31*(D15/($D$24)) -> 0.21935223 | G31: =D31*(D15/($D$24-$D$20)) -> 0.22070602
B32: Bahrain | C32: 7.78 | D32: 9.91 | E32: =C32*(D16/($D$24-$D$20)) -> 0.18917208 | F32: =D32*(D16/($D$24)) -> 0.23948536 | G32: =D32*(D16/($D$24-$D$20)) -> 0.24096341
B33: Qatar | C33: 4.95 | D33: 5.89 | E33: =C33*(D17/($D$24-$D$20)) -> 0.17037992 | F33: =D33*(D17/($D$24)) -> 0.20149134 | G33: =D33*(D17/($D$24-$D$20)) -> 0.2027349
B34: Egypt | C34: 9.42 | D34: 12.41 | E34: =C34*(D18/($D$24-$D$20)) -> 0.75151685 | F34: =D34*(D18/($D$24)) -> 0.98398272 | G34: =D34*(D18/($D$24-$D$20)) -> 0.99005563
B35: Morocco | C35: 6 | D35: 6.96 | E35: =C35*(D19/($D$24-$D$20)) -> 0.058504496 | F35: =D35*(D19/($D$24)) -> 0.067448937 | G35: =D35*(D19/($D$24-$D$20)) -> 0.067865216
B36: Lebanon | C36: 30.89 | D36: 31.62 | E36: 0 | F36: =D36*(D20/($D$24)) -> 0.19395419 | G36: 0
B37: Kazakhstan | C37: 6.01 | D37: 7.01 | E37: =C37*(D21/($D$24-$D$20)) -> 0.32073939 | F37: =D37*(D21/($D$24)) -> 0.37181227 | G37: =D37*(D21/($D$24-$D$20)) -> 0.37410701
B38: Jordan | C38: 8.89 | D38: 10.02 | E38: =C38*(D22/($D$24-$D$20)) -> 0.18396581 | F38: =D38*(D22/($D$24)) -> 0.20607767 | G38: =D38*(D22/($D$24-$D$20)) -> 0.20734954
B39: Iraq | C39: 8.42 | D39: 13.53 | E39: =C39*(D23/($D$24-$D$20)) -> 0.12838724 | F39: =D39*(D23/($D$24)) -> 0.20503852 | G39: =D39*(D23/($D$24-$D$20)) -> 0.20630397
B40: Total / Blended | E40: =SUM(E28:E39) -> 5.9053168 | F40: =SUM(F28:F39) -> 7.1814674 | G40: =SUM(G28:G39) -> 7.0306385
B42: 4 - Exit multiple iteration
B43: Scenario | C43: EV | D43: Equity | E43: D/E | F43: Levered β | G43: D/(D+E) | H43: Kd (wtd) | I43: Ke | J43: Ke (wtd) | K43: WACC | L43: Exit Multiple
B44: Base (Old ERPs) | C44: 8260.66 | D44: =C44-681 -> 7579.66 | E44: =681/D44 -> 0.089845719 | F44: =0.7*(1+((1-0.16)*E44)) -> 0.75282928 | G44: =681/C44 -> 0.082438933 | H44: =6.3%*G44*0.84 -> 0.0043626684 | I44: =4.1%+(F44*E40/100) -> 0.085456954 | J44: =I44*(1-G44) -> 0.078411974 | K44: =J44+H44 -> 0.082774642 | L44: =0.45/((K44)-0.035) -> 9.4192228
B45: Base (New ERPs) | C45: 7097.68 | D45: =C45-681 -> 6416.68 | E45: =681/D45 -> 0.10612965 | F45: =0.7*(1+((1-0.16)*E45)) -> 0.76240423 | G45: =681/C45 -> 0.095946845 | H45: =6.3%*G45*0.84 -> 0.005077507 | I45: =4.1%+(F45*G40/100) -> 0.094601886 | J45: =I45*(1-G45) -> 0.085525133 | K45: =J45+H45 -> 0.09060264 | L45: =0.45/((K45)-0.035) -> 8.0931409
B46: Net debt assumed: 681 (Lease Liability in 2030)
